["[{\"wordAn\":\"*papa\",\"langSubgroupsList\":\"OC\",\"langNamesList\":\"Proto-Micronesian\",\"langNamesCount\":1},{\"wordAn\":\"*papa:n\",\"langSubgroupsList\":\"WMP\",\"langNamesList\":\"Proto-Chamic\",\"langNamesCount\":1},{\"wordAn\":\"a-papan\",\"langSubgroupsList\":\"WMP\",\"langNamesList\":\"\",\"langNamesCount\":1},{\"wordAn\":\"ba-baba\",\"langSubgroupsList\":\"OC\",\"langNamesList\":\"\",\"langNamesCount\":1},{\"wordAn\":\"baba\",\"langSubgroupsList\":\"OC\",\"langNamesList\":\"Manam, Molima, Lau, Gilbertese, Wayan, Kapingamarangi, Nukuoro\",\"langNamesCount\":7,\"latSubgroupMean\":-4.6055,\"longSubgroupMean\":156.2699},{\"wordAn\":\"baba-\",\"langSubgroupsList\":\"OC\",\"langNamesList\":\"Tawala\",\"langNamesCount\":1,\"latSubgroupMean\":-10.3115,\"longSubgroupMean\":150.6439},{\"wordAn\":\"baba-la\",\"langSubgroupsList\":\"OC\",\"langNamesList\":\"\",\"langNamesCount\":1},{\"wordAn\":\"baba-na\",\"langSubgroupsList\":\"OC\",\"langNamesList\":\"\",\"langNamesCount\":1},{\"wordAn\":\"baba hale\",\"langSubgroupsList\":\"OC\",\"langNamesList\":\"\",\"langNamesCount\":1},{\"wordAn\":\"batu papa\",\"langSubgroupsList\":\"WMP\",\"langNamesList\":\"\",\"langNamesCount\":1},{\"wordAn\":\"bava\",\"langSubgroupsList\":\"OC\",\"langNamesList\":\"Fijian\",\"langNamesCount\":1,\"latSubgroupMean\":-17.1843,\"longSubgroupMean\":178.6103},{\"wordAn\":\"fafan\",\"langSubgroupsList\":\"SHWNG, WMP\",\"langNamesList\":\"Buli, Tiruray\",\"langNamesCount\":2,\"latSubgroupMean\":3.783,\"longSubgroupMean\":126.2345},{\"wordAn\":\"fáfana\",\"langSubgroupsList\":\"WMP\",\"langNamesList\":\"Malagasy\",\"langNamesCount\":1},{\"wordAn\":\"faka-papa\",\"langSubgroupsList\":\"OC\",\"langNamesList\":\"\",\"langNamesCount\":1},{\"wordAn\":\"hahane\",\"langSubgroupsList\":\"CMP\",\"langNamesList\":\"Kayeli\",\"langNamesCount\":1},{\"wordAn\":\"hapa\",\"langSubgroupsList\":\"OC\",\"langNamesList\":\"'Are'are, Sa'a, Arosi\",\"langNamesCount\":3,\"latSubgroupMean\":-9.8875,\"longSubgroupMean\":161.5886},{\"wordAn\":\"hoʔo-papa\",\"langSubgroupsList\":\"OC\",\"langNamesList\":\"\",\"langNamesCount\":1},{\"wordAn\":\"kaiwa ba-baba-na\",\"langSubgroupsList\":\"OC\",\"langNamesList\":\"Dobuan\",\"langNamesCount\":1,\"latSubgroupMean\":-9.7087,\"longSubgroupMean\":150.8116},{\"wordAn\":\"ma-mapan\",\"langSubgroupsList\":\"WMP\",\"langNamesList\":\"\",\"langNamesCount\":1},{\"wordAn\":\"n-papan\",\"langSubgroupsList\":\"CMP\",\"langNamesList\":\"Yamdena\",\"langNamesCount\":1,\"latSubgroupMean\":-7.7535,\"longSubgroupMean\":131.2833},{\"wordAn\":\"pɔp\",\"langSubgroupsList\":\"OC\",\"langNamesList\":\"Mokilese\",\"langNamesCount\":1,\"latSubgroupMean\":5.8275,\"longSubgroupMean\":161.7198},{\"wordAn\":\"paap\",\"langSubgroupsList\":\"OC\",\"langNamesList\":\"Chuukese, Puluwat\",\"langNamesCount\":2,\"latSubgroupMean\":7.4529,\"longSubgroupMean\":150.6457},{\"wordAn\":\"paap(a)\",\"langSubgroupsList\":\"OC\",\"langNamesList\":\"Woleaian\",\"langNamesCount\":1,\"latSubgroupMean\":7.9622,\"longSubgroupMean\":146.2538},{\"wordAn\":\"pæp\",\"langSubgroupsList\":\"OC\",\"langNamesList\":\"Kosraean\",\"langNamesCount\":1,\"latSubgroupMean\":5.3,\"longSubgroupMean\":163},{\"wordAn\":\"papa\",\"langSubgroupsList\":\"CMP, OC, WMP\",\"langNamesList\":\"Hawu, Pileni, Rotuman, Tongan, Niue, Futunan, Samoan, Rennellese, Anuta, Maori, Hawaiian, Wolio\",\"langNamesCount\":12,\"latSubgroupMean\":-15.9672,\"longSubgroupMean\":58.9555},{\"wordAn\":\"pápá-n limw\",\"langSubgroupsList\":\"OC\",\"langNamesList\":\"\",\"langNamesCount\":1},{\"wordAn\":\"papaŋ\",\"langSubgroupsList\":\"CMP, WMP\",\"langNamesList\":\"Manggarai, Makassarese\",\"langNamesCount\":2,\"latSubgroupMean\":-6.9893,\"longSubgroupMean\":120.0585},{\"wordAn\":\"papan\",\"langSubgroupsList\":\"CMP, WMP\",\"langNamesList\":\"Buruese, Maranao, Mapun, Yakan, Ngaju Dayak, Iban, Moken, Malay, Gayo, Karo Batak, Toba Batak, Sundanese, Old Javanese, Javanese, Balinese, Sasak, Mongondow, Tae'\",\"langNamesCount\":18,\"latSubgroupMean\":0.0964,\"longSubgroupMean\":111.8317},{\"wordAn\":\"papán\",\"langSubgroupsList\":\"WMP\",\"langNamesList\":\"Cebuano\",\"langNamesCount\":1,\"latSubgroupMean\":10.4338,\"longSubgroupMean\":123.8159},{\"wordAn\":\"papán ŋa bató\",\"langSubgroupsList\":\"WMP\",\"langNamesList\":\"Waray-Waray\",\"langNamesCount\":1,\"latSubgroupMean\":12,\"longSubgroupMean\":125},{\"wordAn\":\"papan batu\",\"langSubgroupsList\":\"WMP\",\"langNamesList\":\"\",\"langNamesCount\":1},{\"wordAn\":\"papan catur\",\"langSubgroupsList\":\"WMP\",\"langNamesList\":\"\",\"langNamesCount\":1},{\"wordAn\":\"papan kayuʔ\",\"langSubgroupsList\":\"WMP\",\"langNamesList\":\"\",\"langNamesCount\":1},{\"wordAn\":\"papan sandar\",\"langSubgroupsList\":\"WMP\",\"langNamesList\":\"\",\"langNamesCount\":1},{\"wordAn\":\"papeuën\",\"langSubgroupsList\":\"WMP\",\"langNamesList\":\"Acehnese\",\"langNamesCount\":1,\"latSubgroupMean\":3.9076,\"longSubgroupMean\":96.6033},{\"wordAn\":\"papeun\",\"langSubgroupsList\":\"WMP\",\"langNamesList\":\"Rejang\",\"langNamesCount\":1,\"latSubgroupMean\":-3.42,\"longSubgroupMean\":102.5},{\"wordAn\":\"papna\",\"langSubgroupsList\":\"CMP\",\"langNamesList\":\"Wetan\",\"langNamesCount\":1},{\"wordAn\":\"pava\",\"langSubgroupsList\":\"OC\",\"langNamesList\":\"Bugotu\",\"langNamesCount\":1,\"latSubgroupMean\":-8.4868,\"longSubgroupMean\":159.8044},{\"wordAn\":\"vaka-baba\",\"langSubgroupsList\":\"OC\",\"langNamesList\":\"\",\"langNamesCount\":1},{\"wordAn\":\"wlawl\",\"langSubgroupsList\":\"WMP\",\"langNamesList\":\"Palauan\",\"langNamesCount\":1,\"latSubgroupMean\":7.4513,\"longSubgroupMean\":134.3402}]"]
