[{"item":"tikus","word":"rat","count":53,"id":102,"group":"Animals"},{"item":"tehu","word":"rat","count":29,"id":102,"group":"Animals"},{"item":"kimoa","word":"rat","count":15,"id":102,"group":"Animals"},{"item":"karam","word":"rat","count":13,"id":102,"group":"Animals"},{"item":"kiore","word":"rat","count":12,"id":102,"group":"Animals"},{"item":"xariβi","word":"rat","count":12,"id":102,"group":"Animals"},{"item":"ariβi","word":"rat","count":11,"id":102,"group":"Animals"},{"item":"tikos","word":"rat","count":11,"id":102,"group":"Animals"},{"item":"kawe","word":"rat","count":9,"id":102,"group":"Animals"},{"item":"n-ariβ","word":"rat","count":9,"id":102,"group":"Animals"},{"item":"nou1","word":"rat","count":9,"id":102,"group":"Animals"},{"item":"βola","word":"rat","count":9,"id":102,"group":"Animals"},{"item":"kariβi","word":"rat","count":8,"id":102,"group":"Animals"},{"item":"kusue","word":"rat","count":8,"id":102,"group":"Animals"},{"item":"ʔasuhe","word":"rat","count":7,"id":102,"group":"Animals"},{"item":"a-kasua","word":"rat","count":7,"id":102,"group":"Animals"},{"item":"nu1","word":"rat","count":7,"id":102,"group":"Animals"},{"item":"sipù","word":"rat","count":7,"id":102,"group":"Animals"},{"item":"ʔambaw","word":"rat","count":6,"id":102,"group":"Animals"},{"item":"ʔasufe","word":"rat","count":6,"id":102,"group":"Animals"},{"item":"asu","word":"rat","count":6,"id":102,"group":"Animals"},{"item":"asua","word":"rat","count":6,"id":102,"group":"Animals"},{"item":"ci:ᵐbwi","word":"rat","count":6,"id":102,"group":"Animals"},{"item":"kahau","word":"rat","count":6,"id":102,"group":"Animals"},{"item":"kairate","word":"rat","count":6,"id":102,"group":"Animals"},{"item":"kwaisalu","word":"rat","count":6,"id":102,"group":"Animals"},{"item":"na-ɣasu","word":"rat","count":6,"id":102,"group":"Animals"},{"item":"na-riv","word":"rat","count":6,"id":102,"group":"Animals"},{"item":"sine","word":"rat","count":6,"id":102,"group":"Animals"},{"item":"tadike","word":"rat","count":6,"id":102,"group":"Animals"},{"item":"tomo","word":"rat","count":6,"id":102,"group":"Animals"},{"item":"*labaw","word":"rat","count":5,"id":102,"group":"Animals"},{"item":"ɣasu","word":"rat","count":5,"id":102,"group":"Animals"},{"item":"ɣusuve","word":"rat","count":5,"id":102,"group":"Animals"},{"item":"ciibwi","word":"rat","count":5,"id":102,"group":"Animals"},{"item":"gorobu","word":"rat","count":5,"id":102,"group":"Animals"},{"item":"husuve","word":"rat","count":5,"id":102,"group":"Animals"},{"item":"ibou","word":"rat","count":5,"id":102,"group":"Animals"},{"item":"kaua","word":"rat","count":5,"id":102,"group":"Animals"},{"item":"kiki","word":"rat","count":5,"id":102,"group":"Animals"},{"item":"kutu","word":"rat","count":5,"id":102,"group":"Animals"},{"item":"na-laᵐbut","word":"rat","count":5,"id":102,"group":"Animals"},{"item":"ɣarivi","word":"rat","count":4,"id":102,"group":"Animals"},{"item":"ɣasuβ","word":"rat","count":4,"id":102,"group":"Animals"},{"item":"ɸola","word":"rat","count":4,"id":102,"group":"Animals"},{"item":"ᵐbʷat karivi","word":"rat","count":4,"id":102,"group":"Animals"},{"item":"arif","word":"rat","count":4,"id":102,"group":"Animals"},{"item":"bita","word":"rat","count":4,"id":102,"group":"Animals"},{"item":"ciᵐbʷi","word":"rat","count":4,"id":102,"group":"Animals"},{"item":"doeke","word":"rat","count":4,"id":102,"group":"Animals"},{"item":"garivi","word":"rat","count":4,"id":102,"group":"Animals"},{"item":"itala","word":"rat","count":4,"id":102,"group":"Animals"},{"item":"kikoni","word":"rat","count":4,"id":102,"group":"Animals"},{"item":"kiso","word":"rat","count":4,"id":102,"group":"Animals"},{"item":"kokolaka","word":"rat","count":4,"id":102,"group":"Animals"},{"item":"kuake","word":"rat","count":4,"id":102,"group":"Animals"},{"item":"kusive","word":"rat","count":4,"id":102,"group":"Animals"},{"item":"kusu","word":"rat","count":4,"id":102,"group":"Animals"},{"item":"kwekweyalu","word":"rat","count":4,"id":102,"group":"Animals"},{"item":"laho","word":"rat","count":4,"id":102,"group":"Animals"},{"item":"malawo","word":"rat","count":4,"id":102,"group":"Animals"},{"item":"nɛ-laᵐbut","word":"rat","count":4,"id":102,"group":"Animals"},{"item":"na-kahu","word":"rat","count":4,"id":102,"group":"Animals"},{"item":"nakusi","word":"rat","count":4,"id":102,"group":"Animals"},{"item":"pʷat-xarifi","word":"rat","count":4,"id":102,"group":"Animals"},{"item":"sikokoi","word":"rat","count":4,"id":102,"group":"Animals"},{"item":"sinmunam","word":"rat","count":4,"id":102,"group":"Animals"},{"item":"teʔu","word":"rat","count":4,"id":102,"group":"Animals"},{"item":"teo","word":"rat","count":4,"id":102,"group":"Animals"},{"item":"uduve","word":"rat","count":4,"id":102,"group":"Animals"},{"item":"waguruma","word":"rat","count":4,"id":102,"group":"Animals"},{"item":"xarivi","word":"rat","count":4,"id":102,"group":"Animals"},{"item":"yahuk","word":"rat","count":4,"id":102,"group":"Animals"},{"item":"zomo","word":"rat","count":4,"id":102,"group":"Animals"},{"item":"'ʔutut","word":"rat","count":3,"id":102,"group":"Animals"},{"item":"*tikus","word":"rat","count":3,"id":102,"group":"Animals"},{"item":"ariβ","word":"rat","count":3,"id":102,"group":"Animals"},{"item":"balau","word":"rat","count":3,"id":102,"group":"Animals"},{"item":"caivak","word":"rat","count":3,"id":102,"group":"Animals"},{"item":"capʷek","word":"rat","count":3,"id":102,"group":"Animals"},{"item":"daga","word":"rat","count":3,"id":102,"group":"Animals"},{"item":"hariβi","word":"rat","count":3,"id":102,"group":"Animals"},{"item":"kadzies","word":"rat","count":3,"id":102,"group":"Animals"},{"item":"kadzys","word":"rat","count":3,"id":102,"group":"Animals"},{"item":"kat̪’apa","word":"rat","count":3,"id":102,"group":"Animals"},{"item":"kat̪ava","word":"rat","count":3,"id":102,"group":"Animals"},{"item":"kih","word":"rat","count":3,"id":102,"group":"Animals"},{"item":"kuhi","word":"rat","count":3,"id":102,"group":"Animals"},{"item":"kurezu","word":"rat","count":3,"id":102,"group":"Animals"},{"item":"kuruve","word":"rat","count":3,"id":102,"group":"Animals"},{"item":"na-ɣahup","word":"rat","count":3,"id":102,"group":"Animals"},{"item":"na-ɣariv","word":"rat","count":3,"id":102,"group":"Animals"},{"item":"na-aswa","word":"rat","count":3,"id":102,"group":"Animals"},{"item":"na-riɸ","word":"rat","count":3,"id":102,"group":"Animals"},{"item":"na-riβ","word":"rat","count":3,"id":102,"group":"Animals"},{"item":"na-xariv","word":"rat","count":3,"id":102,"group":"Animals"},{"item":"Ɵine","word":"rat","count":3,"id":102,"group":"Animals"},{"item":"otot","word":"rat","count":3,"id":102,"group":"Animals"},{"item":"qolic","word":"rat","count":3,"id":102,"group":"Animals"},{"item":"rumat","word":"rat","count":3,"id":102,"group":"Animals"},{"item":"runĵi","word":"rat","count":3,"id":102,"group":"Animals"},{"item":"βolaβo","word":"rat","count":3,"id":102,"group":"Animals"},{"item":"voalàvo","word":"rat","count":3,"id":102,"group":"Animals"},{"item":"xariɸ","word":"rat","count":3,"id":102,"group":"Animals"},{"item":"xarifi","word":"rat","count":3,"id":102,"group":"Animals"},{"item":"xasu","word":"rat","count":3,"id":102,"group":"Animals"},{"item":"'iore","word":"rat","count":2,"id":102,"group":"Animals"},{"item":"'laso","word":"rat","count":2,"id":102,"group":"Animals"},{"item":"'sammil","word":"rat","count":2,"id":102,"group":"Animals"},{"item":"(na)-kkich","word":"rat","count":2,"id":102,"group":"Animals"},{"item":"(naa)-kkich","word":"rat","count":2,"id":102,"group":"Animals"},{"item":"*balabaw","word":"rat","count":2,"id":102,"group":"Animals"},{"item":"*kanzupay","word":"rat","count":2,"id":102,"group":"Animals"},{"item":"*kasupe","word":"rat","count":2,"id":102,"group":"Animals"},{"item":"əskif","word":"rat","count":2,"id":102,"group":"Animals"},{"item":"ɣʉsʉwə","word":"rat","count":2,"id":102,"group":"Animals"},{"item":"ɣariβ","word":"rat","count":2,"id":102,"group":"Animals"},{"item":"ɣariβi","word":"rat","count":2,"id":102,"group":"Animals"},{"item":"ɣasew","word":"rat","count":2,"id":102,"group":"Animals"},{"item":"ɣasuf","word":"rat","count":2,"id":102,"group":"Animals"},{"item":"ɣasuhe","word":"rat","count":2,"id":102,"group":"Animals"},{"item":"ɣasuv","word":"rat","count":2,"id":102,"group":"Animals"},{"item":"ɣasuwe","word":"rat","count":2,"id":102,"group":"Animals"},{"item":"ɣosou","word":"rat","count":2,"id":102,"group":"Animals"},{"item":"ɣusu","word":"rat","count":2,"id":102,"group":"Animals"},{"item":"ɣusuwə","word":"rat","count":2,"id":102,"group":"Animals"},{"item":"ʔambow","word":"rat","count":2,"id":102,"group":"Animals"},{"item":"ʔangbɨʔ","word":"rat","count":2,"id":102,"group":"Animals"},{"item":"ʔasufa","word":"rat","count":2,"id":102,"group":"Animals"},{"item":"ʔuŋe","word":"rat","count":2,"id":102,"group":"Animals"},{"item":"ʔunge","word":"rat","count":2,"id":102,"group":"Animals"},{"item":"ʔungeh","word":"rat","count":2,"id":102,"group":"Animals"},{"item":"ʔutut","word":"rat","count":2,"id":102,"group":"Animals"},{"item":"ʔútut","word":"rat","count":2,"id":102,"group":"Animals"},{"item":"θine","word":"rat","count":2,"id":102,"group":"Animals"},{"item":"ᵐbʷisiᵐbok","word":"rat","count":2,"id":102,"group":"Animals"},{"item":"aitara","word":"rat","count":2,"id":102,"group":"Animals"},{"item":"ambaw","word":"rat","count":2,"id":102,"group":"Animals"},{"item":"angbu","word":"rat","count":2,"id":102,"group":"Animals"},{"item":"bɨ:ki","word":"rat","count":2,"id":102,"group":"Animals"},{"item":"babaw","word":"rat","count":2,"id":102,"group":"Animals"},{"item":"balabáw","word":"rat","count":2,"id":102,"group":"Animals"},{"item":"balabew","word":"rat","count":2,"id":102,"group":"Animals"},{"item":"balakad","word":"rat","count":2,"id":102,"group":"Animals"},{"item":"balakád","word":"rat","count":2,"id":102,"group":"Animals"},{"item":"balao","word":"rat","count":2,"id":102,"group":"Animals"},{"item":"balawaw","word":"rat","count":2,"id":102,"group":"Animals"},{"item":"balawo","word":"rat","count":2,"id":102,"group":"Animals"},{"item":"belabaw","word":"rat","count":2,"id":102,"group":"Animals"},{"item":"caipo","word":"rat","count":2,"id":102,"group":"Animals"},{"item":"capoek","word":"rat","count":2,"id":102,"group":"Animals"},{"item":"çi:ᵐbɨ","word":"rat","count":2,"id":102,"group":"Animals"},{"item":"çi:ᵐbwi","word":"rat","count":2,"id":102,"group":"Animals"},{"item":"dagáq","word":"rat","count":2,"id":102,"group":"Animals"},{"item":"dagis","word":"rat","count":2,"id":102,"group":"Animals"},{"item":"dagís","word":"rat","count":2,"id":102,"group":"Animals"},{"item":"gasuwe","word":"rat","count":2,"id":102,"group":"Animals"},{"item":"ɡaub","word":"rat","count":2,"id":102,"group":"Animals"},{"item":"gimwau","word":"rat","count":2,"id":102,"group":"Animals"},{"item":"ife","word":"rat","count":2,"id":102,"group":"Animals"},{"item":"ilagâ","word":"rat","count":2,"id":102,"group":"Animals"},{"item":"ilo","word":"rat","count":2,"id":102,"group":"Animals"},{"item":"inema","word":"rat","count":2,"id":102,"group":"Animals"},{"item":"iraga","word":"rat","count":2,"id":102,"group":"Animals"},{"item":"iβe","word":"rat","count":2,"id":102,"group":"Animals"},{"item":"kahap","word":"rat","count":2,"id":102,"group":"Animals"},{"item":"kahaw","word":"rat","count":2,"id":102,"group":"Animals"},{"item":"kaitom","word":"rat","count":2,"id":102,"group":"Animals"},{"item":"karám","word":"rat","count":2,"id":102,"group":"Animals"},{"item":"kasuhe","word":"rat","count":2,"id":102,"group":"Animals"},{"item":"kelikeli","word":"rat","count":2,"id":102,"group":"Animals"},{"item":"kelikeli@boduwe","word":"rat","count":2,"id":102,"group":"Animals"},{"item":"kīki","word":"rat","count":2,"id":102,"group":"Animals"},{"item":"kikī","word":"rat","count":2,"id":102,"group":"Animals"},{"item":"kio'e","word":"rat","count":2,"id":102,"group":"Animals"},{"item":"kiole","word":"rat","count":2,"id":102,"group":"Animals"},{"item":"kisue","word":"rat","count":2,"id":102,"group":"Animals"},{"item":"kiue","word":"rat","count":2,"id":102,"group":"Animals"},{"item":"kokolaka@gimwau","word":"rat","count":2,"id":102,"group":"Animals"},{"item":"kotu","word":"rat","count":2,"id":102,"group":"Animals"},{"item":"kumaa","word":"rat","count":2,"id":102,"group":"Animals"},{"item":"kusua","word":"rat","count":2,"id":102,"group":"Animals"},{"item":"kusuke","word":"rat","count":2,"id":102,"group":"Animals"},{"item":"kut","word":"rat","count":2,"id":102,"group":"Animals"},{"item":"kuyu","word":"rat","count":2,"id":102,"group":"Animals"},{"item":"kuzi","word":"rat","count":2,"id":102,"group":"Animals"},{"item":"lɒkipo","word":"rat","count":2,"id":102,"group":"Animals"},{"item":"ləpu","word":"rat","count":2,"id":102,"group":"Animals"},{"item":"laᵐbʊt","word":"rat","count":2,"id":102,"group":"Animals"},{"item":"lakih","word":"rat","count":2,"id":102,"group":"Animals"},{"item":"lœkʌ̃","word":"rat","count":2,"id":102,"group":"Animals"},{"item":"luf","word":"rat","count":2,"id":102,"group":"Animals"},{"item":"ma13 sa35 kue55","word":"rat","count":2,"id":102,"group":"Animals"},{"item":"mbɔhu","word":"rat","count":2,"id":102,"group":"Animals"},{"item":"mdagur","word":"rat","count":2,"id":102,"group":"Animals"},{"item":"mesu","word":"rat","count":2,"id":102,"group":"Animals"},{"item":"minsau","word":"rat","count":2,"id":102,"group":"Animals"},{"item":"monci","word":"rat","count":2,"id":102,"group":"Animals"},{"item":"mutun","word":"rat","count":2,"id":102,"group":"Animals"},{"item":"na-ɣariɸ","word":"rat","count":2,"id":102,"group":"Animals"},{"item":"na-ɣhʊw","word":"rat","count":2,"id":102,"group":"Animals"},{"item":"na-ɣhou","word":"rat","count":2,"id":102,"group":"Animals"},{"item":"na-asua","word":"rat","count":2,"id":102,"group":"Animals"},{"item":"na-azuɔ","word":"rat","count":2,"id":102,"group":"Animals"},{"item":"na-kasua","word":"rat","count":2,"id":102,"group":"Animals"},{"item":"na-rið","word":"rat","count":2,"id":102,"group":"Animals"},{"item":"na-sua","word":"rat","count":2,"id":102,"group":"Animals"},{"item":"na-xarip","word":"rat","count":2,"id":102,"group":"Animals"},{"item":"na-xasu","word":"rat","count":2,"id":102,"group":"Animals"},{"item":"nakkich","word":"rat","count":2,"id":102,"group":"Animals"},{"item":"nau1","word":"rat","count":2,"id":102,"group":"Animals"},{"item":"ne-laᵐbut","word":"rat","count":2,"id":102,"group":"Animals"},{"item":"nei53","word":"rat","count":2,"id":102,"group":"Animals"},{"item":"nelabut","word":"rat","count":2,"id":102,"group":"Animals"},{"item":"nguti","word":"rat","count":2,"id":102,"group":"Animals"},{"item":"no-ɣova","word":"rat","count":2,"id":102,"group":"Animals"},{"item":"no13","word":"rat","count":2,"id":102,"group":"Animals"},{"item":"no3","word":"rat","count":2,"id":102,"group":"Animals"},{"item":"nu:1","word":"rat","count":2,"id":102,"group":"Animals"},{"item":"ombue","word":"rat","count":2,"id":102,"group":"Animals"},{"item":"qoliʔ","word":"rat","count":2,"id":102,"group":"Animals"},{"item":"ria","word":"rat","count":2,"id":102,"group":"Animals"},{"item":"sibu","word":"rat","count":2,"id":102,"group":"Animals"},{"item":"siro","word":"rat","count":2,"id":102,"group":"Animals"},{"item":"siyoi","word":"rat","count":2,"id":102,"group":"Animals"},{"item":"skif","word":"rat","count":2,"id":102,"group":"Animals"},{"item":"βinio","word":"rat","count":2,"id":102,"group":"Animals"},{"item":"tə2 n̥o3","word":"rat","count":2,"id":102,"group":"Animals"},{"item":"takuh","word":"rat","count":2,"id":102,"group":"Animals"},{"item":"tema","word":"rat","count":2,"id":102,"group":"Animals"},{"item":"temwa","word":"rat","count":2,"id":102,"group":"Animals"},{"item":"tikɔs","word":"rat","count":2,"id":102,"group":"Animals"},{"item":"tikʊs","word":"rat","count":2,"id":102,"group":"Animals"},{"item":"uᵐboara","word":"rat","count":2,"id":102,"group":"Animals"},{"item":"ulakih","word":"rat","count":2,"id":102,"group":"Animals"},{"item":"ulakis","word":"rat","count":2,"id":102,"group":"Animals"},{"item":"uruve","word":"rat","count":2,"id":102,"group":"Animals"},{"item":"utot","word":"rat","count":2,"id":102,"group":"Animals"},{"item":"wuyu","word":"rat","count":2,"id":102,"group":"Animals"},{"item":"xʰot̪’ap","word":"rat","count":2,"id":102,"group":"Animals"},{"item":"xʰot̪ap","word":"rat","count":2,"id":102,"group":"Animals"},{"item":"xariβ","word":"rat","count":2,"id":102,"group":"Animals"},{"item":"xasuf","word":"rat","count":2,"id":102,"group":"Animals"},{"item":"xazu","word":"rat","count":2,"id":102,"group":"Animals"},{"item":"xele","word":"rat","count":2,"id":102,"group":"Animals"},{"item":"yasuk","word":"rat","count":2,"id":102,"group":"Animals"},{"item":"'ʋau","word":"rat","count":1,"id":102,"group":"Animals"},{"item":"'ʔambɨw","word":"rat","count":1,"id":102,"group":"Animals"},{"item":"'ʔambaw","word":"rat","count":1,"id":102,"group":"Animals"},{"item":"'ʔotot","word":"rat","count":1,"id":102,"group":"Animals"},{"item":"'ʔutot","word":"rat","count":1,"id":102,"group":"Animals"},{"item":"'flafa","word":"rat","count":1,"id":102,"group":"Animals"},{"item":"'flaha","word":"rat","count":1,"id":102,"group":"Animals"},{"item":"'lawa","word":"rat","count":1,"id":102,"group":"Animals"},{"item":"'loso","word":"rat","count":1,"id":102,"group":"Animals"},{"item":"'mɛlla","word":"rat","count":1,"id":102,"group":"Animals"},{"item":"'mɛlloke","word":"rat","count":1,"id":102,"group":"Animals"},{"item":"'martai","word":"rat","count":1,"id":102,"group":"Animals"},{"item":"'moton","word":"rat","count":1,"id":102,"group":"Animals"},{"item":"'plaho","word":"rat","count":1,"id":102,"group":"Animals"},{"item":"'pop","word":"rat","count":1,"id":102,"group":"Animals"},{"item":"'popiə","word":"rat","count":1,"id":102,"group":"Animals"},{"item":"'popije","word":"rat","count":1,"id":102,"group":"Animals"},{"item":"'βaβo","word":"rat","count":1,"id":102,"group":"Animals"},{"item":"'tikus","word":"rat","count":1,"id":102,"group":"Animals"},{"item":"'upə","word":"rat","count":1,"id":102,"group":"Animals"},{"item":"'ura","word":"rat","count":1,"id":102,"group":"Animals"},{"item":" 'asufe","word":"rat","count":1,"id":102,"group":"Animals"},{"item":" 'iole","word":"rat","count":1,"id":102,"group":"Animals"},{"item":"*[l̥]aʔ","word":"rat","count":1,"id":102,"group":"Animals"},{"item":"*ʰnu: A","word":"rat","count":1,"id":102,"group":"Animals"},{"item":"*ambaw","word":"rat","count":1,"id":102,"group":"Animals"},{"item":"*aniu A","word":"rat","count":1,"id":102,"group":"Animals"},{"item":"*b(V)lesu","word":"rat","count":1,"id":102,"group":"Animals"},{"item":"*babaw","word":"rat","count":1,"id":102,"group":"Animals"},{"item":"*bala(b)o","word":"rat","count":1,"id":102,"group":"Animals"},{"item":"*balesu","word":"rat","count":1,"id":102,"group":"Animals"},{"item":"*bru̯a C","word":"rat","count":1,"id":102,"group":"Animals"},{"item":"*dumpaw","word":"rat","count":1,"id":102,"group":"Animals"},{"item":"*dur","word":"rat","count":1,"id":102,"group":"Animals"},{"item":"*Erum","word":"rat","count":1,"id":102,"group":"Animals"},{"item":"*hlai C","word":"rat","count":1,"id":102,"group":"Animals"},{"item":"*hniw","word":"rat","count":1,"id":102,"group":"Animals"},{"item":"*hnu A1","word":"rat","count":1,"id":102,"group":"Animals"},{"item":"*hnu3","word":"rat","count":1,"id":102,"group":"Animals"},{"item":"*k-r-wak H","word":"rat","count":1,"id":102,"group":"Animals"},{"item":"*k[a]niɛʔ","word":"rat","count":1,"id":102,"group":"Animals"},{"item":"*kəlawo","word":"rat","count":1,"id":102,"group":"Animals"},{"item":"*karam","word":"rat","count":1,"id":102,"group":"Animals"},{"item":"*karivi","word":"rat","count":1,"id":102,"group":"Animals"},{"item":"*kasuve","word":"rat","count":1,"id":102,"group":"Animals"},{"item":"*keci","word":"rat","count":1,"id":102,"group":"Animals"},{"item":"*kliu C1","word":"rat","count":1,"id":102,"group":"Animals"},{"item":"*kn1[i]ʔ","word":"rat","count":1,"id":102,"group":"Animals"},{"item":"*koɭabaw","word":"rat","count":1,"id":102,"group":"Animals"},{"item":"*krwak H","word":"rat","count":1,"id":102,"group":"Animals"},{"item":"*kucuve","word":"rat","count":1,"id":102,"group":"Animals"},{"item":"*kulabaw","word":"rat","count":1,"id":102,"group":"Animals"},{"item":"*kumaa ","word":"rat","count":1,"id":102,"group":"Animals"},{"item":"*kuruve","word":"rat","count":1,"id":102,"group":"Animals"},{"item":"*kusuve","word":"rat","count":1,"id":102,"group":"Animals"},{"item":"*lapo","word":"rat","count":1,"id":102,"group":"Animals"},{"item":"*n’aɣr","word":"rat","count":1,"id":102,"group":"Animals"},{"item":"*naŋ B","word":"rat","count":1,"id":102,"group":"Animals"},{"item":"*nau B","word":"rat","count":1,"id":102,"group":"Animals"},{"item":"*qawlid","word":"rat","count":1,"id":102,"group":"Animals"},{"item":"*quŋih","word":"rat","count":1,"id":102,"group":"Animals"},{"item":"*r-wak","word":"rat","count":1,"id":102,"group":"Animals"},{"item":"*taxuliang","word":"rat","count":1,"id":102,"group":"Animals"},{"item":"*tikuː","word":"rat","count":1,"id":102,"group":"Animals"},{"item":"*walawu","word":"rat","count":1,"id":102,"group":"Animals"},{"item":"[n]oɔ","word":"rat","count":1,"id":102,"group":"Animals"},{"item":"ŋei53","word":"rat","count":1,"id":102,"group":"Animals"},{"item":"ŋeri","word":"rat","count":1,"id":102,"group":"Animals"},{"item":"ŋiro","word":"rat","count":1,"id":102,"group":"Animals"},{"item":"ȵa33 ɕɔ̰35","word":"rat","count":1,"id":102,"group":"Animals"},{"item":"ȵa33 tsa̰ŋ55","word":"rat","count":1,"id":102,"group":"Animals"},{"item":"ɕua24","word":"rat","count":1,"id":102,"group":"Animals"},{"item":"əwɛa","word":"rat","count":1,"id":102,"group":"Animals"},{"item":"ɛ|wu","word":"rat","count":1,"id":102,"group":"Animals"},{"item":"ɛlpo","word":"rat","count":1,"id":102,"group":"Animals"},{"item":"ɣəhuwə","word":"rat","count":1,"id":102,"group":"Animals"},{"item":"ɣáŋgam","word":"rat","count":1,"id":102,"group":"Animals"},{"item":"ɣai seo","word":"rat","count":1,"id":102,"group":"Animals"},{"item":"ɣalɪᵐbit͡soŋ","word":"rat","count":1,"id":102,"group":"Animals"},{"item":"ɣariɣi","word":"rat","count":1,"id":102,"group":"Animals"},{"item":"ɣarið̼̼","word":"rat","count":1,"id":102,"group":"Animals"},{"item":"ɣariv̈","word":"rat","count":1,"id":102,"group":"Animals"},{"item":"ɣarp","word":"rat","count":1,"id":102,"group":"Animals"},{"item":"ɣasou","word":"rat","count":1,"id":102,"group":"Animals"},{"item":"ɣasufe","word":"rat","count":1,"id":102,"group":"Animals"},{"item":"ɣasup","word":"rat","count":1,"id":102,"group":"Animals"},{"item":"ɣirið","word":"rat","count":1,"id":102,"group":"Animals"},{"item":"ɣosow","word":"rat","count":1,"id":102,"group":"Animals"},{"item":"ɣosuɣ","word":"rat","count":1,"id":102,"group":"Animals"},{"item":"ɣuðuve","word":"rat","count":1,"id":102,"group":"Animals"},{"item":"ɣusuw","word":"rat","count":1,"id":102,"group":"Animals"},{"item":"ɣusuwo","word":"rat","count":1,"id":102,"group":"Animals"},{"item":"ɬəi53","word":"rat","count":1,"id":102,"group":"Animals"},{"item":"ɬei55","word":"rat","count":1,"id":102,"group":"Animals"},{"item":"ɬi35","word":"rat","count":1,"id":102,"group":"Animals"},{"item":"ɬjiŋ3","word":"rat","count":1,"id":102,"group":"Animals"},{"item":"ɸulɛke","word":"rat","count":1,"id":102,"group":"Animals"},{"item":"ʂiɣɑn","word":"rat","count":1,"id":102,"group":"Animals"},{"item":"ʃĩ:bǝ","word":"rat","count":1,"id":102,"group":"Animals"},{"item":"ʈo-ɖe","word":"rat","count":1,"id":102,"group":"Animals"},{"item":"ʔaŋbɨʔ","word":"rat","count":1,"id":102,"group":"Animals"},{"item":"ʔaŋbúʔ","word":"rat","count":1,"id":102,"group":"Animals"},{"item":"ʔa0 θi24","word":"rat","count":1,"id":102,"group":"Animals"},{"item":"ʔa0 lja45","word":"rat","count":1,"id":102,"group":"Animals"},{"item":"ʔabaᵒ","word":"rat","count":1,"id":102,"group":"Animals"},{"item":"ʔadús","word":"rat","count":1,"id":102,"group":"Animals"},{"item":"ʔæLohæʃ","word":"rat","count":1,"id":102,"group":"Animals"},{"item":"ʔæwhæʃ","word":"rat","count":1,"id":102,"group":"Animals"},{"item":"ʔakɨd","word":"rat","count":1,"id":102,"group":"Animals"},{"item":"ʔalu'áð","word":"rat","count":1,"id":102,"group":"Animals"},{"item":"ʔambɨw","word":"rat","count":1,"id":102,"group":"Animals"},{"item":"ʔámbaw","word":"rat","count":1,"id":102,"group":"Animals"},{"item":"ʔasuha","word":"rat","count":1,"id":102,"group":"Animals"},{"item":"ʔäwhäs","word":"rat","count":1,"id":102,"group":"Animals"},{"item":"ʔdi243 θi243","word":"rat","count":1,"id":102,"group":"Animals"},{"item":"ʔeda","word":"rat","count":1,"id":102,"group":"Animals"},{"item":"ʔedo","word":"rat","count":1,"id":102,"group":"Animals"},{"item":"ʔi-laha","word":"rat","count":1,"id":102,"group":"Animals"},{"item":"ʔimoa","word":"rat","count":1,"id":102,"group":"Animals"},{"item":"ʔioGe","word":"rat","count":1,"id":102,"group":"Animals"},{"item":"ʔiole","word":"rat","count":1,"id":102,"group":"Animals"},{"item":"ʔiore","word":"rat","count":1,"id":102,"group":"Animals"},{"item":"ʔoŋ51","word":"rat","count":1,"id":102,"group":"Animals"},{"item":"ʔoʔolaʔa","word":"rat","count":1,"id":102,"group":"Animals"},{"item":"ʔólit","word":"rat","count":1,"id":102,"group":"Animals"},{"item":"ʔotot","word":"rat","count":1,"id":102,"group":"Animals"},{"item":"ʔuŋeh","word":"rat","count":1,"id":102,"group":"Animals"},{"item":"ʔuʡəðuʔ","word":"rat","count":1,"id":102,"group":"Animals"},{"item":"ʔudu","word":"rat","count":1,"id":102,"group":"Animals"},{"item":"ʔwaisalu@ʔautoga","word":"rat","count":1,"id":102,"group":"Animals"},{"item":"ʡθuʔ","word":"rat","count":1,"id":102,"group":"Animals"},{"item":"ʡolic","word":"rat","count":1,"id":102,"group":"Animals"},{"item":"ʧɑʃqɑn","word":"rat","count":1,"id":102,"group":"Animals"},{"item":"ʧəʧqan","word":"rat","count":1,"id":102,"group":"Animals"},{"item":"ʨiʨiχaŋ","word":"rat","count":1,"id":102,"group":"Animals"},{"item":"ˀariβi","word":"rat","count":1,"id":102,"group":"Animals"},{"item":"ˁariβ","word":"rat","count":1,"id":102,"group":"Animals"},{"item":"θibaru","word":"rat","count":1,"id":102,"group":"Animals"},{"item":"χunaɢla","word":"rat","count":1,"id":102,"group":"Animals"},{"item":"ҫine","word":"rat","count":1,"id":102,"group":"Animals"},{"item":"ᵐbɪsiᵐbox","word":"rat","count":1,"id":102,"group":"Animals"},{"item":"ᵐbʷisiᵐbɔkʰ","word":"rat","count":1,"id":102,"group":"Animals"},{"item":"ᵐbʷisiᵐbokʰ","word":"rat","count":1,"id":102,"group":"Animals"},{"item":"ᵐbarawe","word":"rat","count":1,"id":102,"group":"Animals"},{"item":"ᵐbatomo","word":"rat","count":1,"id":102,"group":"Animals"},{"item":"ᵐbisiᵐbok","word":"rat","count":1,"id":102,"group":"Animals"},{"item":"ṃ'lawa","word":"rat","count":1,"id":102,"group":"Animals"},{"item":"a-asua","word":"rat","count":1,"id":102,"group":"Animals"},{"item":"a kue","word":"rat","count":1,"id":102,"group":"Animals"},{"item":"a kusupu","word":"rat","count":1,"id":102,"group":"Animals"},{"item":"a wat̪a","word":"rat","count":1,"id":102,"group":"Animals"},{"item":"áŋbu[ʔ]","word":"rat","count":1,"id":102,"group":"Animals"},{"item":"aʃu","word":"rat","count":1,"id":102,"group":"Animals"},{"item":"abʷara","word":"rat","count":1,"id":102,"group":"Animals"},{"item":"abulik","word":"rat","count":1,"id":102,"group":"Animals"},{"item":"aði","word":"rat","count":1,"id":102,"group":"Animals"},{"item":"adombar","word":"rat","count":1,"id":102,"group":"Animals"},{"item":"adus","word":"rat","count":1,"id":102,"group":"Animals"},{"item":"afuno","word":"rat","count":1,"id":102,"group":"Animals"},{"item":"aji","word":"rat","count":1,"id":102,"group":"Animals"},{"item":"akīkī","word":"rat","count":1,"id":102,"group":"Animals"},{"item":"akisova","word":"rat","count":1,"id":102,"group":"Animals"},{"item":"alawu","word":"rat","count":1,"id":102,"group":"Animals"},{"item":"aliŋeket","word":"rat","count":1,"id":102,"group":"Animals"},{"item":"aliβi","word":"rat","count":1,"id":102,"group":"Animals"},{"item":"ambɨ'","word":"rat","count":1,"id":102,"group":"Animals"},{"item":"ambe","word":"rat","count":1,"id":102,"group":"Animals"},{"item":"ambo'","word":"rat","count":1,"id":102,"group":"Animals"},{"item":"ambú","word":"rat","count":1,"id":102,"group":"Animals"},{"item":"angbú","word":"rat","count":1,"id":102,"group":"Animals"},{"item":"ar̃iβi","word":"rat","count":1,"id":102,"group":"Animals"},{"item":"araruru","word":"rat","count":1,"id":102,"group":"Animals"},{"item":"arðia","word":"rat","count":1,"id":102,"group":"Animals"},{"item":"ariv̈","word":"rat","count":1,"id":102,"group":"Animals"},{"item":"ariv̈a","word":"rat","count":1,"id":102,"group":"Animals"},{"item":"ariwi","word":"rat","count":1,"id":102,"group":"Animals"},{"item":"arufe","word":"rat","count":1,"id":102,"group":"Animals"},{"item":"arúha","word":"rat","count":1,"id":102,"group":"Animals"},{"item":"arùha","word":"rat","count":1,"id":102,"group":"Animals"},{"item":"asafái","word":"rat","count":1,"id":102,"group":"Animals"},{"item":"aβí","word":"rat","count":1,"id":102,"group":"Animals"},{"item":"asue","word":"rat","count":1,"id":102,"group":"Animals"},{"item":"asufe","word":"rat","count":1,"id":102,"group":"Animals"},{"item":"asuhe","word":"rat","count":1,"id":102,"group":"Animals"},{"item":"asuβ","word":"rat","count":1,"id":102,"group":"Animals"},{"item":"b'ddek","word":"rat","count":1,"id":102,"group":"Animals"},{"item":"bə|lio","word":"rat","count":1,"id":102,"group":"Animals"},{"item":"bəgaŋ","word":"rat","count":1,"id":102,"group":"Animals"},{"item":"bəlabeow","word":"rat","count":1,"id":102,"group":"Animals"},{"item":"bʌlʌkʌd","word":"rat","count":1,"id":102,"group":"Animals"},{"item":"ba'ǥora","word":"rat","count":1,"id":102,"group":"Animals"},{"item":"baŋgena","word":"rat","count":1,"id":102,"group":"Animals"},{"item":"baɾaßou","word":"rat","count":1,"id":102,"group":"Animals"},{"item":"babo'","word":"rat","count":1,"id":102,"group":"Animals"},{"item":"babow","word":"rat","count":1,"id":102,"group":"Animals"},{"item":"babû","word":"rat","count":1,"id":102,"group":"Animals"},{"item":"babu-a-busum","word":"rat","count":1,"id":102,"group":"Animals"},{"item":"baguduŋ","word":"rat","count":1,"id":102,"group":"Animals"},{"item":"balabaw","word":"rat","count":1,"id":102,"group":"Animals"},{"item":"balafai","word":"rat","count":1,"id":102,"group":"Animals"},{"item":"balagting","word":"rat","count":1,"id":102,"group":"Animals"},{"item":"balakag","word":"rat","count":1,"id":102,"group":"Animals"},{"item":"balawau","word":"rat","count":1,"id":102,"group":"Animals"},{"item":"banggedung","word":"rat","count":1,"id":102,"group":"Animals"},{"item":"barawe","word":"rat","count":1,"id":102,"group":"Animals"},{"item":"bas","word":"rat","count":1,"id":102,"group":"Animals"},{"item":"beáb","word":"rat","count":1,"id":102,"group":"Animals"},{"item":"belab","word":"rat","count":1,"id":102,"group":"Animals"},{"item":"belawo","word":"rat","count":1,"id":102,"group":"Animals"},{"item":"Beleso'","word":"rat","count":1,"id":102,"group":"Animals"},{"item":"belitit","word":"rat","count":1,"id":102,"group":"Animals"},{"item":"beurit","word":"rat","count":1,"id":102,"group":"Animals"},{"item":"bikul","word":"rat","count":1,"id":102,"group":"Animals"},{"item":"bilakad","word":"rat","count":1,"id":102,"group":"Animals"},{"item":"biroet","word":"rat","count":1,"id":102,"group":"Animals"},{"item":"birog","word":"rat","count":1,"id":102,"group":"Animals"},{"item":"blavow","word":"rat","count":1,"id":102,"group":"Animals"},{"item":"bo'piɛ","word":"rat","count":1,"id":102,"group":"Animals"},{"item":"boŋgukut","word":"rat","count":1,"id":102,"group":"Animals"},{"item":"bobot","word":"rat","count":1,"id":102,"group":"Animals"},{"item":"boi11","word":"rat","count":1,"id":102,"group":"Animals"},{"item":"bokoti","word":"rat","count":1,"id":102,"group":"Animals"},{"item":"bokotiʔ","word":"rat","count":1,"id":102,"group":"Animals"},{"item":"bolabow","word":"rat","count":1,"id":102,"group":"Animals"},{"item":"borokoko","word":"rat","count":1,"id":102,"group":"Animals"},{"item":"boroq","word":"rat","count":1,"id":102,"group":"Animals"},{"item":"boyod","word":"rat","count":1,"id":102,"group":"Animals"},{"item":"búhci","word":"rat","count":1,"id":102,"group":"Animals"},{"item":"bukət","word":"rat","count":1,"id":102,"group":"Animals"},{"item":"bukát","word":"rat","count":1,"id":102,"group":"Animals"},{"item":"bukoti","word":"rat","count":1,"id":102,"group":"Animals"},{"item":"buót","word":"rat","count":1,"id":102,"group":"Animals"},{"item":"burʔabu","word":"rat","count":1,"id":102,"group":"Animals"},{"item":"busiᵐbok","word":"rat","count":1,"id":102,"group":"Animals"},{"item":"butit","word":"rat","count":1,"id":102,"group":"Animals"},{"item":"buxci","word":"rat","count":1,"id":102,"group":"Animals"},{"item":"bwauʔai","word":"rat","count":1,"id":102,"group":"Animals"},{"item":"bwisibok","word":"rat","count":1,"id":102,"group":"Animals"},{"item":"caːco","word":"rat","count":1,"id":102,"group":"Animals"},{"item":"cawek","word":"rat","count":1,"id":102,"group":"Animals"},{"item":"cha'ka","word":"rat","count":1,"id":102,"group":"Animals"},{"item":"chuột","word":"rat","count":1,"id":102,"group":"Animals"},{"item":"ci:˥bwi˥","word":"rat","count":1,"id":102,"group":"Animals"},{"item":"ci:˦ᵐbwi˦","word":"rat","count":1,"id":102,"group":"Animals"},{"item":"cĩ:ᵐbu","word":"rat","count":1,"id":102,"group":"Animals"},{"item":"ci:bǝ","word":"rat","count":1,"id":102,"group":"Animals"},{"item":"çĩ:bǝ","word":"rat","count":1,"id":102,"group":"Animals"},{"item":"ciᵐbi","word":"rat","count":1,"id":102,"group":"Animals"},{"item":"ciᵐbo","word":"rat","count":1,"id":102,"group":"Animals"},{"item":"cibu","word":"rat","count":1,"id":102,"group":"Animals"},{"item":"cicic","word":"rat","count":1,"id":102,"group":"Animals"},{"item":"ciibwin","word":"rat","count":1,"id":102,"group":"Animals"},{"item":"cit","word":"rat","count":1,"id":102,"group":"Animals"},{"item":"cura","word":"rat","count":1,"id":102,"group":"Animals"},{"item":"da'gi","word":"rat","count":1,"id":102,"group":"Animals"},{"item":"dadâ","word":"rat","count":1,"id":102,"group":"Animals"},{"item":"dadik","word":"rat","count":1,"id":102,"group":"Animals"},{"item":"dagá'","word":"rat","count":1,"id":102,"group":"Animals"},{"item":"dagâ","word":"rat","count":1,"id":102,"group":"Animals"},{"item":"dagih","word":"rat","count":1,"id":102,"group":"Animals"},{"item":"dahiwa","word":"rat","count":1,"id":102,"group":"Animals"},{"item":"dajua","word":"rat","count":1,"id":102,"group":"Animals"},{"item":"dekeh","word":"rat","count":1,"id":102,"group":"Animals"},{"item":"dheke","word":"rat","count":1,"id":102,"group":"Animals"},{"item":"dhéké","word":"rat","count":1,"id":102,"group":"Animals"},{"item":"diggis","word":"rat","count":1,"id":102,"group":"Animals"},{"item":"digoŋ","word":"rat","count":1,"id":102,"group":"Animals"},{"item":"doʔʔo","word":"rat","count":1,"id":102,"group":"Animals"},{"item":"doziro","word":"rat","count":1,"id":102,"group":"Animals"},{"item":"ðuɣuve","word":"rat","count":1,"id":102,"group":"Animals"},{"item":"du54","word":"rat","count":1,"id":102,"group":"Animals"},{"item":"dúmpaw","word":"rat","count":1,"id":102,"group":"Animals"},{"item":"dur","word":"rat","count":1,"id":102,"group":"Animals"},{"item":"dura","word":"rat","count":1,"id":102,"group":"Animals"},{"item":"duu13","word":"rat","count":1,"id":102,"group":"Animals"},{"item":"e kusuke","word":"rat","count":1,"id":102,"group":"Animals"},{"item":"eech","word":"rat","count":1,"id":102,"group":"Animals"},{"item":"èhoewā","word":"rat","count":1,"id":102,"group":"Animals"},{"item":"ekarik","word":"rat","count":1,"id":102,"group":"Animals"},{"item":"ekiue","word":"rat","count":1,"id":102,"group":"Animals"},{"item":"emtit asit","word":"rat","count":1,"id":102,"group":"Animals"},{"item":"èpèhĕja","word":"rat","count":1,"id":102,"group":"Animals"},{"item":"ewaw","word":"rat","count":1,"id":102,"group":"Animals"},{"item":"eyoare","word":"rat","count":1,"id":102,"group":"Animals"},{"item":"fisɛl","word":"rat","count":1,"id":102,"group":"Animals"},{"item":"fōitau","word":"rat","count":1,"id":102,"group":"Animals"},{"item":"folafa","word":"rat","count":1,"id":102,"group":"Animals"},{"item":"fondē","word":"rat","count":1,"id":102,"group":"Animals"},{"item":"fsɛi","word":"rat","count":1,"id":102,"group":"Animals"},{"item":"fusel","word":"rat","count":1,"id":102,"group":"Animals"},{"item":"gabeláu","word":"rat","count":1,"id":102,"group":"Animals"},{"item":"gag","word":"rat","count":1,"id":102,"group":"Animals"},{"item":"galang","word":"rat","count":1,"id":102,"group":"Animals"},{"item":"gamboxam","word":"rat","count":1,"id":102,"group":"Animals"},{"item":"ɡambuam","word":"rat","count":1,"id":102,"group":"Animals"},{"item":"gandaw","word":"rat","count":1,"id":102,"group":"Animals"},{"item":"gando","word":"rat","count":1,"id":102,"group":"Animals"},{"item":"gasifou","word":"rat","count":1,"id":102,"group":"Animals"},{"item":"ge'lew","word":"rat","count":1,"id":102,"group":"Animals"},{"item":"geeʀ","word":"rat","count":1,"id":102,"group":"Animals"},{"item":"geech","word":"rat","count":1,"id":102,"group":"Animals"},{"item":"geeshi","word":"rat","count":1,"id":102,"group":"Animals"},{"item":"gei","word":"rat","count":1,"id":102,"group":"Animals"},{"item":"geme","word":"rat","count":1,"id":102,"group":"Animals"},{"item":"geshɪ","word":"rat","count":1,"id":102,"group":"Animals"},{"item":"geshi-","word":"rat","count":1,"id":102,"group":"Animals"},{"item":"gheech","word":"rat","count":1,"id":102,"group":"Animals"},{"item":"gheesch","word":"rat","count":1,"id":102,"group":"Animals"},{"item":"gheesh","word":"rat","count":1,"id":102,"group":"Animals"},{"item":"gimau","word":"rat","count":1,"id":102,"group":"Animals"},{"item":"gimwau@gimau","word":"rat","count":1,"id":102,"group":"Animals"},{"item":"gisap","word":"rat","count":1,"id":102,"group":"Animals"},{"item":"gobe","word":"rat","count":1,"id":102,"group":"Animals"},{"item":"gok gok","word":"rat","count":1,"id":102,"group":"Animals"},{"item":"goua","word":"rat","count":1,"id":102,"group":"Animals"},{"item":"gut","word":"rat","count":1,"id":102,"group":"Animals"},{"item":"gwaŋ","word":"rat","count":1,"id":102,"group":"Animals"},{"item":"gwaua","word":"rat","count":1,"id":102,"group":"Animals"},{"item":"hɔ44","word":"rat","count":1,"id":102,"group":"Animals"},{"item":"hɔriβi","word":"rat","count":1,"id":102,"group":"Animals"},{"item":"haɾiv","word":"rat","count":1,"id":102,"group":"Animals"},{"item":"habətarə","word":"rat","count":1,"id":102,"group":"Animals"},{"item":"harip˺","word":"rat","count":1,"id":102,"group":"Animals"},{"item":"hariβ̆","word":"rat","count":1,"id":102,"group":"Animals"},{"item":"harivi","word":"rat","count":1,"id":102,"group":"Animals"},{"item":"hĕnchä̃","word":"rat","count":1,"id":102,"group":"Animals"},{"item":"ho̲n","word":"rat","count":1,"id":102,"group":"Animals"},{"item":"hua33","word":"rat","count":1,"id":102,"group":"Animals"},{"item":"iahukw","word":"rat","count":1,"id":102,"group":"Animals"},{"item":"idube","word":"rat","count":1,"id":102,"group":"Animals"},{"item":"iesukw","word":"rat","count":1,"id":102,"group":"Animals"},{"item":"ifɔ","word":"rat","count":1,"id":102,"group":"Animals"},{"item":"ikumododo","word":"rat","count":1,"id":102,"group":"Animals"},{"item":"ílagâ","word":"rat","count":1,"id":102,"group":"Animals"},{"item":"ilaha","word":"rat","count":1,"id":102,"group":"Animals"},{"item":"imoa","word":"rat","count":1,"id":102,"group":"Animals"},{"item":"in-ɣeθo","word":"rat","count":1,"id":102,"group":"Animals"},{"item":"inɣeθo","word":"rat","count":1,"id":102,"group":"Animals"},{"item":"iole","word":"rat","count":1,"id":102,"group":"Animals"},{"item":"isu","word":"rat","count":1,"id":102,"group":"Animals"},{"item":"jɞ:ʃ","word":"rat","count":1,"id":102,"group":"Animals"},{"item":"jom","word":"rat","count":1,"id":102,"group":"Animals"},{"item":"jumunu","word":"rat","count":1,"id":102,"group":"Animals"},{"item":"k'kuih","word":"rat","count":1,"id":102,"group":"Animals"},{"item":"kɑndol","word":"rat","count":1,"id":102,"group":"Animals"},{"item":"kɔmɔ","word":"rat","count":1,"id":102,"group":"Animals"},{"item":"kəopə","word":"rat","count":1,"id":102,"group":"Animals"},{"item":"kəpéi","word":"rat","count":1,"id":102,"group":"Animals"},{"item":"kɯ2 ken4","word":"rat","count":1,"id":102,"group":"Animals"},{"item":"kʰubiliki","word":"rat","count":1,"id":102,"group":"Animals"},{"item":"ka·p","word":"rat","count":1,"id":102,"group":"Animals"},{"item":"kaboe-kaboe","word":"rat","count":1,"id":102,"group":"Animals"},{"item":"kago","word":"rat","count":1,"id":102,"group":"Animals"},{"item":"kágoh","word":"rat","count":1,"id":102,"group":"Animals"},{"item":"kagox","word":"rat","count":1,"id":102,"group":"Animals"},{"item":"kahu","word":"rat","count":1,"id":102,"group":"Animals"},{"item":"kairaðe","word":"rat","count":1,"id":102,"group":"Animals"},{"item":"kalaʔu","word":"rat","count":1,"id":102,"group":"Animals"},{"item":"kalau","word":"rat","count":1,"id":102,"group":"Animals"},{"item":"kalavo","word":"rat","count":1,"id":102,"group":"Animals"},{"item":"kalawu","word":"rat","count":1,"id":102,"group":"Animals"},{"item":"kalof","word":"rat","count":1,"id":102,"group":"Animals"},{"item":"kalufa","word":"rat","count":1,"id":102,"group":"Animals"},{"item":"kaminde","word":"rat","count":1,"id":102,"group":"Animals"},{"item":"kap","word":"rat","count":1,"id":102,"group":"Animals"},{"item":"kapa","word":"rat","count":1,"id":102,"group":"Animals"},{"item":"kapit","word":"rat","count":1,"id":102,"group":"Animals"},{"item":"karawo","word":"rat","count":1,"id":102,"group":"Animals"},{"item":"kareyk","word":"rat","count":1,"id":102,"group":"Animals"},{"item":"kari","word":"rat","count":1,"id":102,"group":"Animals"},{"item":"karif","word":"rat","count":1,"id":102,"group":"Animals"},{"item":"karifi","word":"rat","count":1,"id":102,"group":"Animals"},{"item":"kariβ","word":"rat","count":1,"id":102,"group":"Animals"},{"item":"kariβi̥","word":"rat","count":1,"id":102,"group":"Animals"},{"item":"kartɔw","word":"rat","count":1,"id":102,"group":"Animals"},{"item":"kartow","word":"rat","count":1,"id":102,"group":"Animals"},{"item":"karu","word":"rat","count":1,"id":102,"group":"Animals"},{"item":"karuʔ","word":"rat","count":1,"id":102,"group":"Animals"},{"item":"karuje","word":"rat","count":1,"id":102,"group":"Animals"},{"item":"kasu","word":"rat","count":1,"id":102,"group":"Animals"},{"item":"kasua","word":"rat","count":1,"id":102,"group":"Animals"},{"item":"katone","word":"rat","count":1,"id":102,"group":"Animals"},{"item":"kau","word":"rat","count":1,"id":102,"group":"Animals"},{"item":"kaule","word":"rat","count":1,"id":102,"group":"Animals"},{"item":"kawat","word":"rat","count":1,"id":102,"group":"Animals"},{"item":"kawok","word":"rat","count":1,"id":102,"group":"Animals"},{"item":"keɓuku","word":"rat","count":1,"id":102,"group":"Animals"},{"item":"keʀe-(n)","word":"rat","count":1,"id":102,"group":"Animals"},{"item":"keʀekeʀ","word":"rat","count":1,"id":102,"group":"Animals"},{"item":"keʀekeʀi-(n)","word":"rat","count":1,"id":102,"group":"Animals"},{"item":"keeʀ","word":"rat","count":1,"id":102,"group":"Animals"},{"item":"keesi","word":"rat","count":1,"id":102,"group":"Animals"},{"item":"kéjôe","word":"rat","count":1,"id":102,"group":"Animals"},{"item":"keriβ","word":"rat","count":1,"id":102,"group":"Animals"},{"item":"keromé","word":"rat","count":1,"id":102,"group":"Animals"},{"item":"kesɪ","word":"rat","count":1,"id":102,"group":"Animals"},{"item":"kesi-","word":"rat","count":1,"id":102,"group":"Animals"},{"item":"keusu","word":"rat","count":1,"id":102,"group":"Animals"},{"item":"kĕwānoe","word":"rat","count":1,"id":102,"group":"Animals"},{"item":"khukumade","word":"rat","count":1,"id":102,"group":"Animals"},{"item":"khukumede","word":"rat","count":1,"id":102,"group":"Animals"},{"item":"kifəbun (f)","word":"rat","count":1,"id":102,"group":"Animals"},{"item":"kifəma (m)","word":"rat","count":1,"id":102,"group":"Animals"},{"item":"kihsrihk","word":"rat","count":1,"id":102,"group":"Animals"},{"item":"kij-dik","word":"rat","count":1,"id":102,"group":"Animals"},{"item":"kijdik","word":"rat","count":1,"id":102,"group":"Animals"},{"item":"kije-sik","word":"rat","count":1,"id":102,"group":"Animals"},{"item":"kīkī","word":"rat","count":1,"id":102,"group":"Animals"},{"item":"kikiʔi","word":"rat","count":1,"id":102,"group":"Animals"},{"item":"kimo","word":"rat","count":1,"id":102,"group":"Animals"},{"item":"kimóa","word":"rat","count":1,"id":102,"group":"Animals"},{"item":"kinó","word":"rat","count":1,"id":102,"group":"Animals"},{"item":"kioŋe","word":"rat","count":1,"id":102,"group":"Animals"},{"item":"kioʔe","word":"rat","count":1,"id":102,"group":"Animals"},{"item":"kioge","word":"rat","count":1,"id":102,"group":"Animals"},{"item":"kiole ","word":"rat","count":1,"id":102,"group":"Animals"},{"item":"kiora","word":"rat","count":1,"id":102,"group":"Animals"},{"item":"kire","word":"rat","count":1,"id":102,"group":"Animals"},{"item":"kisap","word":"rat","count":1,"id":102,"group":"Animals"},{"item":"kisrik","word":"rat","count":1,"id":102,"group":"Animals"},{"item":"kisuo","word":"rat","count":1,"id":102,"group":"Animals"},{"item":"kitik","word":"rat","count":1,"id":102,"group":"Animals"},{"item":"kjaŋ53 kjaŋ44","word":"rat","count":1,"id":102,"group":"Animals"},{"item":"kji:u3","word":"rat","count":1,"id":102,"group":"Animals"},{"item":"kji:u3 lie:k8","word":"rat","count":1,"id":102,"group":"Animals"},{"item":"kla24","word":"rat","count":1,"id":102,"group":"Animals"},{"item":"klah","word":"rat","count":1,"id":102,"group":"Animals"},{"item":"knɛ̃ʔ","word":"rat","count":1,"id":102,"group":"Animals"},{"item":"koɭabaw","word":"rat","count":1,"id":102,"group":"Animals"},{"item":"koɭavao","word":"rat","count":1,"id":102,"group":"Animals"},{"item":"koabaw","word":"rat","count":1,"id":102,"group":"Animals"},{"item":"kœnǰ","word":"rat","count":1,"id":102,"group":"Animals"},{"item":"kœnĵ","word":"rat","count":1,"id":102,"group":"Animals"},{"item":"kofiata","word":"rat","count":1,"id":102,"group":"Animals"},{"item":"kolape","word":"rat","count":1,"id":102,"group":"Animals"},{"item":"komo","word":"rat","count":1,"id":102,"group":"Animals"},{"item":"kopwa","word":"rat","count":1,"id":102,"group":"Animals"},{"item":"korrkarr korrkarr","word":"rat","count":1,"id":102,"group":"Animals"},{"item":"koto","word":"rat","count":1,"id":102,"group":"Animals"},{"item":"koup","word":"rat","count":1,"id":102,"group":"Animals"},{"item":"kovi","word":"rat","count":1,"id":102,"group":"Animals"},{"item":"ku'yɨng","word":"rat","count":1,"id":102,"group":"Animals"},{"item":"kuəup","word":"rat","count":1,"id":102,"group":"Animals"},{"item":"kubiliki","word":"rat","count":1,"id":102,"group":"Animals"},{"item":"kucuve","word":"rat","count":1,"id":102,"group":"Animals"},{"item":"kudeke","word":"rat","count":1,"id":102,"group":"Animals"},{"item":"kue","word":"rat","count":1,"id":102,"group":"Animals"},{"item":"kues","word":"rat","count":1,"id":102,"group":"Animals"},{"item":"kuǥuḏe","word":"rat","count":1,"id":102,"group":"Animals"},{"item":"kuho","word":"rat","count":1,"id":102,"group":"Animals"},{"item":"kuhoo","word":"rat","count":1,"id":102,"group":"Animals"},{"item":"kui ~ kwi","word":"rat","count":1,"id":102,"group":"Animals"},{"item":"kuj","word":"rat","count":1,"id":102,"group":"Animals"},{"item":"kukaha","word":"rat","count":1,"id":102,"group":"Animals"},{"item":"kukudeʔeke","word":"rat","count":1,"id":102,"group":"Animals"},{"item":"kukum","word":"rat","count":1,"id":102,"group":"Animals"},{"item":"kulafaw","word":"rat","count":1,"id":102,"group":"Animals"},{"item":"kulavau","word":"rat","count":1,"id":102,"group":"Animals"},{"item":"kulavaw","word":"rat","count":1,"id":102,"group":"Animals"},{"item":"kuluβe","word":"rat","count":1,"id":102,"group":"Animals"},{"item":"kumā","word":"rat","count":1,"id":102,"group":"Animals"},{"item":"kuma","word":"rat","count":1,"id":102,"group":"Animals"},{"item":"kumakuma","word":"rat","count":1,"id":102,"group":"Animals"},{"item":"kumari","word":"rat","count":1,"id":102,"group":"Animals"},{"item":"kunĵu","word":"rat","count":1,"id":102,"group":"Animals"},{"item":"kup","word":"rat","count":1,"id":102,"group":"Animals"},{"item":"kurabaw","word":"rat","count":1,"id":102,"group":"Animals"},{"item":"kurabo","word":"rat","count":1,"id":102,"group":"Animals"},{"item":"kuragbeŋ","word":"rat","count":1,"id":102,"group":"Animals"},{"item":"kure@moli","word":"rat","count":1,"id":102,"group":"Animals"},{"item":"kureve","word":"rat","count":1,"id":102,"group":"Animals"},{"item":"kuruke","word":"rat","count":1,"id":102,"group":"Animals"},{"item":"kuse","word":"rat","count":1,"id":102,"group":"Animals"},{"item":"kusi","word":"rat","count":1,"id":102,"group":"Animals"},{"item":"kusia","word":"rat","count":1,"id":102,"group":"Animals"},{"item":"kusoi","word":"rat","count":1,"id":102,"group":"Animals"},{"item":"kusukui","word":"rat","count":1,"id":102,"group":"Animals"},{"item":"kusup","word":"rat","count":1,"id":102,"group":"Animals"},{"item":"kusuva","word":"rat","count":1,"id":102,"group":"Animals"},{"item":"kuwíl","word":"rat","count":1,"id":102,"group":"Animals"},{"item":"kuyang","word":"rat","count":1,"id":102,"group":"Animals"},{"item":"kuyoŋ","word":"rat","count":1,"id":102,"group":"Animals"},{"item":"kuyuyu","word":"rat","count":1,"id":102,"group":"Animals"},{"item":"kuzu","word":"rat","count":1,"id":102,"group":"Animals"},{"item":"kwekweanu","word":"rat","count":1,"id":102,"group":"Animals"},{"item":"kwi","word":"rat","count":1,"id":102,"group":"Animals"},{"item":"lɒ55","word":"rat","count":1,"id":102,"group":"Animals"},{"item":"lɔ55","word":"rat","count":1,"id":102,"group":"Animals"},{"item":"ləpo","word":"rat","count":1,"id":102,"group":"Animals"},{"item":"lɪpo","word":"rat","count":1,"id":102,"group":"Animals"},{"item":"lạj6","word":"rat","count":1,"id":102,"group":"Animals"},{"item":"la:ᵐbʊt","word":"rat","count":1,"id":102,"group":"Animals"},{"item":"la’ik kmori","word":"rat","count":1,"id":102,"group":"Animals"},{"item":"laᵐbɔ","word":"rat","count":1,"id":102,"group":"Animals"},{"item":"laᵐbʷɔ","word":"rat","count":1,"id":102,"group":"Animals"},{"item":"laᵐbat","word":"rat","count":1,"id":102,"group":"Animals"},{"item":"laᵐboa","word":"rat","count":1,"id":102,"group":"Animals"},{"item":"laᵐbut","word":"rat","count":1,"id":102,"group":"Animals"},{"item":"la31","word":"rat","count":1,"id":102,"group":"Animals"},{"item":"laabət","word":"rat","count":1,"id":102,"group":"Animals"},{"item":"labət","word":"rat","count":1,"id":102,"group":"Animals"},{"item":"labo","word":"rat","count":1,"id":102,"group":"Animals"},{"item":"labo iʔék","word":"rat","count":1,"id":102,"group":"Animals"},{"item":"lafo","word":"rat","count":1,"id":102,"group":"Animals"},{"item":"lahŏ","word":"rat","count":1,"id":102,"group":"Animals"},{"item":"lai24","word":"rat","count":1,"id":102,"group":"Animals"},{"item":"lai423","word":"rat","count":1,"id":102,"group":"Animals"},{"item":"lak8 nu4","word":"rat","count":1,"id":102,"group":"Animals"},{"item":"lamasoed","word":"rat","count":1,"id":102,"group":"Animals"},{"item":"lambut","word":"rat","count":1,"id":102,"group":"Animals"},{"item":"langsä","word":"rat","count":1,"id":102,"group":"Animals"},{"item":"lâpu","word":"rat","count":1,"id":102,"group":"Animals"},{"item":"laput","word":"rat","count":1,"id":102,"group":"Animals"},{"item":"lasu","word":"rat","count":1,"id":102,"group":"Animals"},{"item":"lat31 tsaai53","word":"rat","count":1,"id":102,"group":"Animals"},{"item":"lauuɕə","word":"rat","count":1,"id":102,"group":"Animals"},{"item":"lavo","word":"rat","count":1,"id":102,"group":"Animals"},{"item":"lepuu","word":"rat","count":1,"id":102,"group":"Animals"},{"item":"lesooq","word":"rat","count":1,"id":102,"group":"Animals"},{"item":"li54","word":"rat","count":1,"id":102,"group":"Animals"},{"item":"lja44","word":"rat","count":1,"id":102,"group":"Animals"},{"item":"loa","word":"rat","count":1,"id":102,"group":"Animals"},{"item":"lu1","word":"rat","count":1,"id":102,"group":"Animals"},{"item":"lua","word":"rat","count":1,"id":102,"group":"Animals"},{"item":"lua-k'udu","word":"rat","count":1,"id":102,"group":"Animals"},{"item":"m`53 ɬo53","word":"rat","count":1,"id":102,"group":"Animals"},{"item":"mə53","word":"rat","count":1,"id":102,"group":"Animals"},{"item":"məncayʔ","word":"rat","count":1,"id":102,"group":"Animals"},{"item":"mənceyt","word":"rat","count":1,"id":102,"group":"Animals"},{"item":"məncit","word":"rat","count":1,"id":102,"group":"Animals"},{"item":"məsəᵐbʷok","word":"rat","count":1,"id":102,"group":"Animals"},{"item":"məsiñco","word":"rat","count":1,"id":102,"group":"Animals"},{"item":"mɛsi","word":"rat","count":1,"id":102,"group":"Animals"},{"item":"ma|laha","word":"rat","count":1,"id":102,"group":"Animals"},{"item":"maɬavaw","word":"rat","count":1,"id":102,"group":"Animals"},{"item":"ma35 sa55 kue43","word":"rat","count":1,"id":102,"group":"Animals"},{"item":"ma42 ɬja35","word":"rat","count":1,"id":102,"group":"Animals"},{"item":"madzeats","word":"rat","count":1,"id":102,"group":"Animals"},{"item":"mai³³niu²¹","word":"rat","count":1,"id":102,"group":"Animals"},{"item":"makal","word":"rat","count":1,"id":102,"group":"Animals"},{"item":"makas(a)","word":"rat","count":1,"id":102,"group":"Animals"},{"item":"malafaw","word":"rat","count":1,"id":102,"group":"Animals"},{"item":"malagho","word":"rat","count":1,"id":102,"group":"Animals"},{"item":"malaha","word":"rat","count":1,"id":102,"group":"Animals"},{"item":"malahaʔe","word":"rat","count":1,"id":102,"group":"Animals"},{"item":"malau","word":"rat","count":1,"id":102,"group":"Animals"},{"item":"malawu","word":"rat","count":1,"id":102,"group":"Animals"},{"item":"malogho","word":"rat","count":1,"id":102,"group":"Animals"},{"item":"mam31 ði45","word":"rat","count":1,"id":102,"group":"Animals"},{"item":"manavoy","word":"rat","count":1,"id":102,"group":"Animals"},{"item":"manciʔ","word":"rat","count":1,"id":102,"group":"Animals"},{"item":"manovan","word":"rat","count":1,"id":102,"group":"Animals"},{"item":"mar'ton","word":"rat","count":1,"id":102,"group":"Animals"},{"item":"mashmash","word":"rat","count":1,"id":102,"group":"Animals"},{"item":"maβakwe","word":"rat","count":1,"id":102,"group":"Animals"},{"item":"mattaro","word":"rat","count":1,"id":102,"group":"Animals"},{"item":"mau53","word":"rat","count":1,"id":102,"group":"Animals"},{"item":"mauka","word":"rat","count":1,"id":102,"group":"Animals"},{"item":"mboɣu","word":"rat","count":1,"id":102,"group":"Animals"},{"item":"mbohu","word":"rat","count":1,"id":102,"group":"Animals"},{"item":"mbrulei","word":"rat","count":1,"id":102,"group":"Animals"},{"item":"mbue","word":"rat","count":1,"id":102,"group":"Animals"},{"item":"mdahalo","word":"rat","count":1,"id":102,"group":"Animals"},{"item":"mei6 nu1","word":"rat","count":1,"id":102,"group":"Animals"},{"item":"mellek","word":"rat","count":1,"id":102,"group":"Animals"},{"item":"melukét","word":"rat","count":1,"id":102,"group":"Animals"},{"item":"menci","word":"rat","count":1,"id":102,"group":"Animals"},{"item":"merep","word":"rat","count":1,"id":102,"group":"Animals"},{"item":"mi|lava","word":"rat","count":1,"id":102,"group":"Animals"},{"item":"milava","word":"rat","count":1,"id":102,"group":"Animals"},{"item":"misiᵐbok","word":"rat","count":1,"id":102,"group":"Animals"},{"item":"mla:báw","word":"rat","count":1,"id":102,"group":"Animals"},{"item":"mlaba'we","word":"rat","count":1,"id":102,"group":"Animals"},{"item":"mo42 lo42","word":"rat","count":1,"id":102,"group":"Animals"},{"item":"moso","word":"rat","count":1,"id":102,"group":"Animals"},{"item":"motə́n","word":"rat","count":1,"id":102,"group":"Animals"},{"item":"motci","word":"rat","count":1,"id":102,"group":"Animals"},{"item":"moton","word":"rat","count":1,"id":102,"group":"Animals"},{"item":"mu:tún","word":"rat","count":1,"id":102,"group":"Animals"},{"item":"mu53","word":"rat","count":1,"id":102,"group":"Animals"},{"item":"muaŋom","word":"rat","count":1,"id":102,"group":"Animals"},{"item":"mun","word":"rat","count":1,"id":102,"group":"Animals"},{"item":"musiŋ","word":"rat","count":1,"id":102,"group":"Animals"},{"item":"mwelesÌ©","word":"rat","count":1,"id":102,"group":"Animals"},{"item":"n-ɣʊsʊw","word":"rat","count":1,"id":102,"group":"Animals"},{"item":"n-asua","word":"rat","count":1,"id":102,"group":"Animals"},{"item":"n-asue","word":"rat","count":1,"id":102,"group":"Animals"},{"item":"n-laᵐbut","word":"rat","count":1,"id":102,"group":"Animals"},{"item":"nɔ3","word":"rat","count":1,"id":102,"group":"Animals"},{"item":"nɔeˀ","word":"rat","count":1,"id":102,"group":"Animals"},{"item":"nə-xasu","word":"rat","count":1,"id":102,"group":"Animals"},{"item":"nəŋ4","word":"rat","count":1,"id":102,"group":"Animals"},{"item":"nəu1","word":"rat","count":1,"id":102,"group":"Animals"},{"item":"n̥ɔ1","word":"rat","count":1,"id":102,"group":"Animals"},{"item":"n̥ɔ3","word":"rat","count":1,"id":102,"group":"Animals"},{"item":"n̥o3","word":"rat","count":1,"id":102,"group":"Animals"},{"item":"na-ɣarif","word":"rat","count":1,"id":102,"group":"Animals"},{"item":"na-ɣarip","word":"rat","count":1,"id":102,"group":"Animals"},{"item":"na-ɣariβ","word":"rat","count":1,"id":102,"group":"Animals"},{"item":"na-ɣariv ⁿdɪknali","word":"rat","count":1,"id":102,"group":"Animals"},{"item":"na-ɾið","word":"rat","count":1,"id":102,"group":"Animals"},{"item":"na-ʔahop","word":"rat","count":1,"id":102,"group":"Animals"},{"item":"na-ahup˺","word":"rat","count":1,"id":102,"group":"Animals"},{"item":"na-laᵐʙʊt","word":"rat","count":1,"id":102,"group":"Animals"},{"item":"na-laᵐʙut","word":"rat","count":1,"id":102,"group":"Animals"},{"item":"na-suɔ","word":"rat","count":1,"id":102,"group":"Animals"},{"item":"na-xaɾəv","word":"rat","count":1,"id":102,"group":"Animals"},{"item":"na-xaɾiv","word":"rat","count":1,"id":102,"group":"Animals"},{"item":"na-xariv ᵐbʷɪlt͡son","word":"rat","count":1,"id":102,"group":"Animals"},{"item":"na 11 ku 55","word":"rat","count":1,"id":102,"group":"Animals"},{"item":"na 4","word":"rat","count":1,"id":102,"group":"Animals"},{"item":"na:u231","word":"rat","count":1,"id":102,"group":"Animals"},{"item":"naŋ31","word":"rat","count":1,"id":102,"group":"Animals"},{"item":"nai5","word":"rat","count":1,"id":102,"group":"Animals"},{"item":"nakhude","word":"rat","count":1,"id":102,"group":"Animals"},{"item":"nakhusi","word":"rat","count":1,"id":102,"group":"Animals"},{"item":"nakih","word":"rat","count":1,"id":102,"group":"Animals"},{"item":"nakiue","word":"rat","count":1,"id":102,"group":"Animals"},{"item":"nam1","word":"rat","count":1,"id":102,"group":"Animals"},{"item":"nao","word":"rat","count":1,"id":102,"group":"Animals"},{"item":"nāve","word":"rat","count":1,"id":102,"group":"Animals"},{"item":"ⁿdu cawek","word":"rat","count":1,"id":102,"group":"Animals"},{"item":"ne","word":"rat","count":1,"id":102,"group":"Animals"},{"item":"ne-xasu","word":"rat","count":1,"id":102,"group":"Animals"},{"item":"ne53ʔ","word":"rat","count":1,"id":102,"group":"Animals"},{"item":"nelemput","word":"rat","count":1,"id":102,"group":"Animals"},{"item":"nen31","word":"rat","count":1,"id":102,"group":"Animals"},{"item":"nensau","word":"rat","count":1,"id":102,"group":"Animals"},{"item":"ni-ᵐbusᵐboh","word":"rat","count":1,"id":102,"group":"Animals"},{"item":"ni-lɛᵐbut","word":"rat","count":1,"id":102,"group":"Animals"},{"item":"niᵐbʷisᵐbox","word":"rat","count":1,"id":102,"group":"Animals"},{"item":"ni22 kjo31","word":"rat","count":1,"id":102,"group":"Animals"},{"item":"ni4 n̥o3","word":"rat","count":1,"id":102,"group":"Animals"},{"item":"nirua","word":"rat","count":1,"id":102,"group":"Animals"},{"item":"nǰapuŋgə","word":"rat","count":1,"id":102,"group":"Animals"},{"item":"nji4","word":"rat","count":1,"id":102,"group":"Animals"},{"item":"njongnjang","word":"rat","count":1,"id":102,"group":"Animals"},{"item":"nouvo","word":"rat","count":1,"id":102,"group":"Animals"},{"item":"nteβita","word":"rat","count":1,"id":102,"group":"Animals"},{"item":"nu:2","word":"rat","count":1,"id":102,"group":"Animals"},{"item":"nu:5","word":"rat","count":1,"id":102,"group":"Animals"},{"item":"nu:6","word":"rat","count":1,"id":102,"group":"Animals"},{"item":"nŭː","word":"rat","count":1,"id":102,"group":"Animals"},{"item":"nui4","word":"rat","count":1,"id":102,"group":"Animals"},{"item":"o'oure","word":"rat","count":1,"id":102,"group":"Animals"},{"item":"oər","word":"rat","count":1,"id":102,"group":"Animals"},{"item":"oʔure","word":"rat","count":1,"id":102,"group":"Animals"},{"item":"obong","word":"rat","count":1,"id":102,"group":"Animals"},{"item":"onei","word":"rat","count":1,"id":102,"group":"Animals"},{"item":"or-roma/smela","word":"rat","count":1,"id":102,"group":"Animals"},{"item":"ornohe","word":"rat","count":1,"id":102,"group":"Animals"},{"item":"ørø sipù","word":"rat","count":1,"id":102,"group":"Animals"},{"item":"pʷiley","word":"rat","count":1,"id":102,"group":"Animals"},{"item":"pʷilip","word":"rat","count":1,"id":102,"group":"Animals"},{"item":"pa'laho","word":"rat","count":1,"id":102,"group":"Animals"},{"item":"patulóy","word":"rat","count":1,"id":102,"group":"Animals"},{"item":"peʔombua","word":"rat","count":1,"id":102,"group":"Animals"},{"item":"pija","word":"rat","count":1,"id":102,"group":"Animals"},{"item":"polu","word":"rat","count":1,"id":102,"group":"Animals"},{"item":"pucol","word":"rat","count":1,"id":102,"group":"Animals"},{"item":"pucon","word":"rat","count":1,"id":102,"group":"Animals"},{"item":"pupurudu","word":"rat","count":1,"id":102,"group":"Animals"},{"item":"qa năj3","word":"rat","count":1,"id":102,"group":"Animals"},{"item":"qa0 ɕi54","word":"rat","count":1,"id":102,"group":"Animals"},{"item":"qa33 nai33","word":"rat","count":1,"id":102,"group":"Animals"},{"item":"qamutic","word":"rat","count":1,"id":102,"group":"Animals"},{"item":"qawlit","word":"rat","count":1,"id":102,"group":"Animals"},{"item":"qólit","word":"rat","count":1,"id":102,"group":"Animals"},{"item":"quinô","word":"rat","count":1,"id":102,"group":"Animals"},{"item":"quliʔ","word":"rat","count":1,"id":102,"group":"Animals"},{"item":"qusiu","word":"rat","count":1,"id":102,"group":"Animals"},{"item":"rɔnĵi","word":"rat","count":1,"id":102,"group":"Animals"},{"item":"rɔzi","word":"rat","count":1,"id":102,"group":"Animals"},{"item":"rariao","word":"rat","count":1,"id":102,"group":"Animals"},{"item":"ratazana","word":"rat","count":1,"id":102,"group":"Animals"},{"item":"rate","word":"rat","count":1,"id":102,"group":"Animals"},{"item":"Ratuvutuvul","word":"rat","count":1,"id":102,"group":"Animals"},{"item":"robēfrar","word":"rat","count":1,"id":102,"group":"Animals"},{"item":"runji","word":"rat","count":1,"id":102,"group":"Animals"},{"item":"runĵl","word":"rat","count":1,"id":102,"group":"Animals"},{"item":"ruzi","word":"rat","count":1,"id":102,"group":"Animals"},{"item":"səfe","word":"rat","count":1,"id":102,"group":"Animals"},{"item":"sɯdʐɯɣan","word":"rat","count":1,"id":102,"group":"Animals"},{"item":"sa'mela","word":"rat","count":1,"id":102,"group":"Animals"},{"item":"safsɛf","word":"rat","count":1,"id":102,"group":"Animals"},{"item":"sau","word":"rat","count":1,"id":102,"group":"Animals"},{"item":"sawo","word":"rat","count":1,"id":102,"group":"Animals"},{"item":"selekep","word":"rat","count":1,"id":102,"group":"Animals"},{"item":"sfe","word":"rat","count":1,"id":102,"group":"Animals"},{"item":"si:pɯ","word":"rat","count":1,"id":102,"group":"Animals"},{"item":"siʧqʌn","word":"rat","count":1,"id":102,"group":"Animals"},{"item":"siᵐbe","word":"rat","count":1,"id":102,"group":"Animals"},{"item":"siᵐbui","word":"rat","count":1,"id":102,"group":"Animals"},{"item":"sihud","word":"rat","count":1,"id":102,"group":"Animals"},{"item":"sikut litun","word":"rat","count":1,"id":102,"group":"Animals"},{"item":"sîsili","word":"rat","count":1,"id":102,"group":"Animals"},{"item":"soroai","word":"rat","count":1,"id":102,"group":"Animals"},{"item":"souwe","word":"rat","count":1,"id":102,"group":"Animals"},{"item":"sowe","word":"rat","count":1,"id":102,"group":"Animals"},{"item":"βʑɯ","word":"rat","count":1,"id":102,"group":"Animals"},{"item":"βaḷaβo","word":"rat","count":1,"id":102,"group":"Animals"},{"item":"βolɛke","word":"rat","count":1,"id":102,"group":"Animals"},{"item":"βulaβo","word":"rat","count":1,"id":102,"group":"Animals"},{"item":"βulehuʔ","word":"rat","count":1,"id":102,"group":"Animals"},{"item":"su55","word":"rat","count":1,"id":102,"group":"Animals"},{"item":"tɔmɔ","word":"rat","count":1,"id":102,"group":"Animals"},{"item":"təʃqɑn","word":"rat","count":1,"id":102,"group":"Animals"},{"item":"təʧqɑn","word":"rat","count":1,"id":102,"group":"Animals"},{"item":"təlíkiʔ","word":"rat","count":1,"id":102,"group":"Animals"},{"item":"tɪkʊs","word":"rat","count":1,"id":102,"group":"Animals"},{"item":"tˢino","word":"rat","count":1,"id":102,"group":"Animals"},{"item":"t̪ep","word":"rat","count":1,"id":102,"group":"Animals"},{"item":"taŋ35 neŋ22","word":"rat","count":1,"id":102,"group":"Animals"},{"item":"tagelobu","word":"rat","count":1,"id":102,"group":"Animals"},{"item":"tagonliang","word":"rat","count":1,"id":102,"group":"Animals"},{"item":"tagouliang","word":"rat","count":1,"id":102,"group":"Animals"},{"item":"taloboco","word":"rat","count":1,"id":102,"group":"Animals"},{"item":"taluvucu","word":"rat","count":1,"id":102,"group":"Animals"},{"item":"tampaʔukað","word":"rat","count":1,"id":102,"group":"Animals"},{"item":"tampahukað","word":"rat","count":1,"id":102,"group":"Animals"},{"item":"tampuhukað","word":"rat","count":1,"id":102,"group":"Animals"},{"item":"taβaʔue","word":"rat","count":1,"id":102,"group":"Animals"},{"item":"taxuliang","word":"rat","count":1,"id":102,"group":"Animals"},{"item":"tecooss","word":"rat","count":1,"id":102,"group":"Animals"},{"item":"tei","word":"rat","count":1,"id":102,"group":"Animals"},{"item":"tekos","word":"rat","count":1,"id":102,"group":"Animals"},{"item":"tékós","word":"rat","count":1,"id":102,"group":"Animals"},{"item":"temʷa","word":"rat","count":1,"id":102,"group":"Animals"},{"item":"tep","word":"rat","count":1,"id":102,"group":"Animals"},{"item":"teu","word":"rat","count":1,"id":102,"group":"Animals"},{"item":"téu","word":"rat","count":1,"id":102,"group":"Animals"},{"item":"ticuh","word":"rat","count":1,"id":102,"group":"Animals"},{"item":"tikis","word":"rat","count":1,"id":102,"group":"Animals"},{"item":"tikoh","word":"rat","count":1,"id":102,"group":"Animals"},{"item":"tikoih","word":"rat","count":1,"id":102,"group":"Animals"},{"item":"tiku:","word":"rat","count":1,"id":102,"group":"Animals"},{"item":"tikuː","word":"rat","count":1,"id":102,"group":"Animals"},{"item":"tíkusuʔ","word":"rat","count":1,"id":102,"group":"Animals"},{"item":"titmʷo","word":"rat","count":1,"id":102,"group":"Animals"},{"item":"titmô","word":"rat","count":1,"id":102,"group":"Animals"},{"item":"tiu","word":"rat","count":1,"id":102,"group":"Animals"},{"item":"tiuʔ","word":"rat","count":1,"id":102,"group":"Animals"},{"item":"tiu1","word":"rat","count":1,"id":102,"group":"Animals"},{"item":"toŋiŋi","word":"rat","count":1,"id":102,"group":"Animals"},{"item":"toa","word":"rat","count":1,"id":102,"group":"Animals"},{"item":"tơkuih","word":"rat","count":1,"id":102,"group":"Animals"},{"item":"tuŋiŋi","word":"rat","count":1,"id":102,"group":"Animals"},{"item":"tu0 va:u52","word":"rat","count":1,"id":102,"group":"Animals"},{"item":"tubung","word":"rat","count":1,"id":102,"group":"Animals"},{"item":"tustus","word":"rat","count":1,"id":102,"group":"Animals"},{"item":"tutus","word":"rat","count":1,"id":102,"group":"Animals"},{"item":"tutús","word":"rat","count":1,"id":102,"group":"Animals"},{"item":"udu","word":"rat","count":1,"id":102,"group":"Animals"},{"item":"ulak","word":"rat","count":1,"id":102,"group":"Animals"},{"item":"upmela","word":"rat","count":1,"id":102,"group":"Animals"},{"item":"usuh","word":"rat","count":1,"id":102,"group":"Animals"},{"item":"usuko","word":"rat","count":1,"id":102,"group":"Animals"},{"item":"utut","word":"rat","count":1,"id":102,"group":"Animals"},{"item":"útut","word":"rat","count":1,"id":102,"group":"Animals"},{"item":"uvilɔ","word":"rat","count":1,"id":102,"group":"Animals"},{"item":"uvilo","word":"rat","count":1,"id":102,"group":"Animals"},{"item":"uzuβ","word":"rat","count":1,"id":102,"group":"Animals"},{"item":"va55 ȵiau55","word":"rat","count":1,"id":102,"group":"Animals"},{"item":"valàvo","word":"rat","count":1,"id":102,"group":"Animals"},{"item":"voalávo","word":"rat","count":1,"id":102,"group":"Animals"},{"item":"voi","word":"rat","count":1,"id":102,"group":"Animals"},{"item":"waŋgar","word":"rat","count":1,"id":102,"group":"Animals"},{"item":"wagilita","word":"rat","count":1,"id":102,"group":"Animals"},{"item":"walawaw","word":"rat","count":1,"id":102,"group":"Animals"},{"item":"walesu","word":"rat","count":1,"id":102,"group":"Animals"},{"item":"wančuruma","word":"rat","count":1,"id":102,"group":"Animals"},{"item":"wanggar","word":"rat","count":1,"id":102,"group":"Animals"},{"item":"wanjudma","word":"rat","count":1,"id":102,"group":"Animals"},{"item":"wanom","word":"rat","count":1,"id":102,"group":"Animals"},{"item":"wantuɾma","word":"rat","count":1,"id":102,"group":"Animals"},{"item":"wasou","word":"rat","count":1,"id":102,"group":"Animals"},{"item":"wawala","word":"rat","count":1,"id":102,"group":"Animals"},{"item":"wãwařa","word":"rat","count":1,"id":102,"group":"Animals"},{"item":"wohow","word":"rat","count":1,"id":102,"group":"Animals"},{"item":"wolavo","word":"rat","count":1,"id":102,"group":"Animals"},{"item":"wolaw","word":"rat","count":1,"id":102,"group":"Animals"},{"item":"wolawu","word":"rat","count":1,"id":102,"group":"Animals"},{"item":"wota","word":"rat","count":1,"id":102,"group":"Animals"},{"item":"wulawo","word":"rat","count":1,"id":102,"group":"Animals"},{"item":"wusu","word":"rat","count":1,"id":102,"group":"Animals"},{"item":"xɷlgăn","word":"rat","count":1,"id":102,"group":"Animals"},{"item":"xʰi","word":"rat","count":1,"id":102,"group":"Animals"},{"item":"xarəβ","word":"rat","count":1,"id":102,"group":"Animals"},{"item":"xarið̼̼","word":"rat","count":1,"id":102,"group":"Animals"},{"item":"xarip","word":"rat","count":1,"id":102,"group":"Animals"},{"item":"xarip̚","word":"rat","count":1,"id":102,"group":"Animals"},{"item":"xariβ̆","word":"rat","count":1,"id":102,"group":"Animals"},{"item":"xariv","word":"rat","count":1,"id":102,"group":"Animals"},{"item":"xasuɸ","word":"rat","count":1,"id":102,"group":"Animals"},{"item":"xasuʰ","word":"rat","count":1,"id":102,"group":"Animals"},{"item":"xasuβ","word":"rat","count":1,"id":102,"group":"Animals"},{"item":"xe","word":"rat","count":1,"id":102,"group":"Animals"},{"item":"xeli","word":"rat","count":1,"id":102,"group":"Animals"},{"item":"xosou","word":"rat","count":1,"id":102,"group":"Animals"},{"item":"xoβa","word":"rat","count":1,"id":102,"group":"Animals"},{"item":"xova","word":"rat","count":1,"id":102,"group":"Animals"},{"item":"yagâ","word":"rat","count":1,"id":102,"group":"Animals"},{"item":"yahaku","word":"rat","count":1,"id":102,"group":"Animals"},{"item":"yatot","word":"rat","count":1,"id":102,"group":"Animals"},{"item":"yatót","word":"rat","count":1,"id":102,"group":"Animals"},{"item":"yeŋgut","word":"rat","count":1,"id":102,"group":"Animals"},{"item":"yeʀekeʀ","word":"rat","count":1,"id":102,"group":"Animals"},{"item":"yesou","word":"rat","count":1,"id":102,"group":"Animals"},{"item":"yesuk","word":"rat","count":1,"id":102,"group":"Animals"},{"item":"yiŋgut","word":"rat","count":1,"id":102,"group":"Animals"},{"item":"yiβe","word":"rat","count":1,"id":102,"group":"Animals"},{"item":"yúi","word":"rat","count":1,"id":102,"group":"Animals"}]
