["[{\"wordEn\":\"basin\",\"wordAn\":\"bisin\",\"langSubgroup\":\"WMP\",\"langName\":\"Manobo (Western Bukidnon)\",\"wordEnLong\":\"basin\",\"setnote\":\"Borrowing from English.\",\"origin\":\"English\",\"originForeign\":true},{\"wordEn\":\"basin\",\"wordAn\":\"bisin\",\"langSubgroup\":\"WMP\",\"langName\":\"Kelabit\",\"wordEnLong\":\"basin\",\"setnote\":\"Borrowing from English.\",\"origin\":\"English\",\"originForeign\":true,\"langISOCode\":\"kzi\",\"langISOLink\":\"http://www.ethnologue.com/show_language.asp?code=kzi\",\"langLocation\":\"Malaysia (Sarawak)\",\"lat\":3.67,\"long\":115.42},{\"wordEn\":\"basin\",\"wordAn\":\"bisin\",\"langSubgroup\":\"WMP\",\"langName\":\"Kayan\",\"wordEnLong\":\"basin\",\"setnote\":\"Borrowing from English.\",\"origin\":\"English\",\"originForeign\":true},{\"wordEn\":\"basin\",\"wordAn\":\"bisin\",\"langSubgroup\":\"WMP\",\"langName\":\"Iban\",\"wordEnLong\":\"basin, large bowl\",\"setnote\":\"Borrowing from English.\",\"origin\":\"English\",\"originForeign\":true,\"langISOCode\":\"iba\",\"langISOLink\":\"http://www.ethnologue.com/show_language.asp?code=iba\",\"langLocation\":\"Malaysia (Sarawak)\",\"lat\":0.5273,\"long\":112.7197},{\"wordEn\":\"basin\",\"wordAn\":\"palaŋgan-aʔ\",\"langSubgroup\":\"WMP\",\"langName\":\"Maranao\",\"wordEnLong\":\"basin\",\"setnote\":\"Borrowing, ultimate from Spanishpalangana 'basin'.\",\"origin\":\"Spanish\",\"originForeign\":true,\"langISOCode\":\"mrw\",\"langISOLink\":\"http://www.ethnologue.com/show_language.asp?code=mrw\",\"langLocation\":\"Philippines\",\"lat\":7.7219,\"long\":124.1455},{\"wordEn\":\"basin\",\"wordAn\":\"palaŋga\",\"langSubgroup\":\"WMP\",\"langName\":\"Wolio\",\"wordEnLong\":\"large basin, wash-basin\",\"setnote\":\"Borrowing, ultimate from Spanishpalangana 'basin'.\",\"origin\":\"Spanish\",\"originForeign\":true,\"langISOCode\":\"wlo\",\"langISOLink\":\"http://www.ethnologue.com/show_language.asp?code=wlo\",\"langLocation\":\"Indonesia (Sulawesi)\",\"lat\":-5.7649,\"long\":123.8989}]"]
