["[{\"wordEn\":\"spelling\",\"wordAn\":\"éja\",\"langSubgroup\":\"WMP\",\"langName\":\"Malay\",\"wordEnLong\":\"spelling, orthography\",\"setnote\":\"Borrowing, ultimately from Arabic.\",\"origin\":\"Arabic\",\"originForeign\":true,\"langISOCode\":\"zlm\",\"langISOLink\":\"http://www.ethnologue.com/show_language.asp?code=zlm\",\"langLocation\":\"Malaysia (Peninsular)\",\"lat\":3.1667,\"long\":101.7},{\"wordEn\":\"spelling\",\"wordAn\":\"éja\",\"langSubgroup\":\"WMP\",\"langName\":\"Malay\",\"wordEnLong\":\"spelling, orthography\",\"setnote\":\"Borrowing, ultimately from Arabic.\",\"origin\":\"Arabic\",\"originForeign\":true,\"langISOCode\":\"zlm\",\"langISOLink\":\"http://www.ethnologue.com/show_language.asp?code=zlm\",\"langLocation\":\"Malaysia (Peninsular)\"},{\"wordEn\":\"spelling\",\"wordAn\":\"éja\",\"langSubgroup\":\"WMP\",\"langName\":\"Sasak\",\"wordEnLong\":\"spelling\",\"setnote\":\"Borrowing, ultimately from Arabic.\",\"origin\":\"Arabic\",\"originForeign\":true,\"langISOCode\":\"sas\",\"langISOLink\":\"http://www.ethnologue.com/show_language.asp?code=sas\",\"langLocation\":\"Indonesia (Nusa Tenggara)\",\"lat\":-8.6679,\"long\":116.2793},{\"wordEn\":\"spelling\",\"wordAn\":\"iʔja\",\"langSubgroup\":\"WMP\",\"langName\":\"Makassarese\",\"wordEnLong\":\"spelling\",\"setnote\":\"Borrowing, ultimately from Arabic.\",\"origin\":\"Arabic\",\"originForeign\":true,\"langISOCode\":\"mak\",\"langISOName\":\"Makasar\",\"langISOLink\":\"http://www.ethnologue.com/show_language.asp?code=mak\",\"langLocation\":\"Indonesia (Sulawesi)\",\"lat\":-5.441,\"long\":119.5312}]"]
