["[{\"wordEn\":\"support:   monetary support\",\"wordAn\":\"biayá\",\"langSubgroup\":\"WMP\",\"langName\":\"Kankanaey\",\"wordEnLong\":\"abundant, plentiful, high (applied to water)\",\"setnote\":\"Borrowing, ultimately from Sanskrit.\",\"origin\":\"Sanskrit\",\"originForeign\":true,\"langISOCode\":\"kne\",\"langISOLink\":\"http://www.ethnologue.com/show_language.asp?code=kne\",\"langLocation\":\"Philippines\",\"lat\":16.8548,\"long\":120.6892},{\"wordEn\":\"support:   monetary support\",\"wordAn\":\"biyáya\",\"langSubgroup\":\"WMP\",\"langName\":\"Casiguran Dumagat\",\"wordEnLong\":\"grace, blessing, mercy, favor (God is always the source of this concept; refers mainly to God's supplying of food),\",\"setnote\":\"Borrowing, ultimately from Sanskrit.\",\"origin\":\"Sanskrit\",\"originForeign\":true,\"langISOCode\":\"dgc\",\"langISOName\":\"Agta, Casiguran Dumagat\",\"langISOLink\":\"http://www.ethnologue.com/show_language.asp?code=dgc\",\"langLocation\":\"Philippines\",\"lat\":16.7835,\"long\":122.0142},{\"wordEn\":\"support:   monetary support\",\"wordAn\":\"biyáyaʔ\",\"langSubgroup\":\"WMP\",\"langName\":\"Tagalog\",\"wordEnLong\":\"grace; favor; blessings, bounty\",\"setnote\":\"Borrowing, ultimately from Sanskrit.\",\"origin\":\"Sanskrit\",\"originForeign\":true,\"langISOCode\":\"tgl\",\"langISOLink\":\"http://www.ethnologue.com/show_language.asp?code=tgl\",\"langLocation\":\"Philippines\",\"lat\":14.1111,\"long\":121.8793},{\"wordEn\":\"support:   monetary support\",\"wordAn\":\"biyáyaʔ\",\"langSubgroup\":\"WMP\",\"langName\":\"Tagalog\",\"wordEnLong\":\"grace; favor; blessings, bounty\",\"setnote\":\"Borrowing, ultimately from Sanskrit.\",\"origin\":\"Sanskrit\",\"originForeign\":true,\"langISOCode\":\"tgl\",\"langISOLink\":\"http://www.ethnologue.com/show_language.asp?code=tgl\",\"langLocation\":\"Philippines\",\"lat\":14.5623,\"long\":121.0693},{\"wordEn\":\"support:   monetary support\",\"wordAn\":\"biyáyaʔ\",\"langSubgroup\":\"WMP\",\"langName\":\"Tagalog\",\"wordEnLong\":\"grace; favor; blessings, bounty\",\"setnote\":\"Borrowing, ultimately from Sanskrit.\",\"origin\":\"Sanskrit\",\"originForeign\":true,\"langISOCode\":\"tgl\",\"langISOLink\":\"http://www.ethnologue.com/show_language.asp?code=tgl\",\"langLocation\":\"Philippines\",\"lat\":15,\"long\":121},{\"wordEn\":\"support:   monetary support\",\"wordAn\":\"biyáyaʔ\",\"langSubgroup\":\"WMP\",\"langName\":\"Tagalog\",\"wordEnLong\":\"grace; favor; blessings, bounty\",\"setnote\":\"Borrowing, ultimately from Sanskrit.\",\"origin\":\"Sanskrit\",\"originForeign\":true,\"langISOCode\":\"tgl\",\"langISOLink\":\"http://www.ethnologue.com/show_language.asp?code=tgl\",\"langLocation\":\"Philippines\"},{\"wordEn\":\"support:   monetary support\",\"wordAn\":\"biaya, biyáya\",\"langSubgroup\":\"WMP\",\"langName\":\"Bikol\",\"wordEnLong\":\"grace, blessing; generous; show generosity toward\",\"setnote\":\"Borrowing, ultimately from Sanskrit.\",\"origin\":\"Sanskrit\",\"originForeign\":true,\"langISOCode\":\"bik\",\"langISOLink\":\"http://www.ethnologue.com/show_language.asp?code=bik\",\"langLocation\":\"Philippines\"},{\"wordEn\":\"support:   monetary support\",\"wordAn\":\"biaya\",\"langSubgroup\":\"WMP\",\"langName\":\"Malay\",\"wordEnLong\":\"disbursement; working expenses; working capital. Of the cost of running a poultry-farm; of money spent on building a mosque; of it being impossible to spend on pleasure on earth and lay up treasure in heaven with the same money\",\"setnote\":\"Borrowing, ultimately from Sanskrit.\",\"origin\":\"Sanskrit\",\"originForeign\":true,\"langISOCode\":\"zlm\",\"langISOLink\":\"http://www.ethnologue.com/show_language.asp?code=zlm\",\"langLocation\":\"Malaysia (Peninsular)\",\"lat\":3.1667,\"long\":101.7},{\"wordEn\":\"support:   monetary support\",\"wordAn\":\"biaya\",\"langSubgroup\":\"WMP\",\"langName\":\"Malay\",\"wordEnLong\":\"disbursement; working expenses; working capital. Of the cost of running a poultry-farm; of money spent on building a mosque; of it being impossible to spend on pleasure on earth and lay up treasure in heaven with the same money\",\"setnote\":\"Borrowing, ultimately from Sanskrit.\",\"origin\":\"Sanskrit\",\"originForeign\":true,\"langISOCode\":\"zlm\",\"langISOLink\":\"http://www.ethnologue.com/show_language.asp?code=zlm\",\"langLocation\":\"Malaysia (Peninsular)\"},{\"wordEn\":\"support:   monetary support\",\"wordAn\":\"biaya\",\"langSubgroup\":\"WMP\",\"langName\":\"Acehnese\",\"wordEnLong\":\"expenses, costs; gifts\",\"setnote\":\"Borrowing, ultimately from Sanskrit.\",\"origin\":\"Sanskrit\",\"originForeign\":true,\"langISOCode\":\"ace\",\"langISOName\":\"Aceh\",\"langISOLink\":\"http://www.ethnologue.com/show_language.asp?code=ace\",\"langLocation\":\"Indonesia (Sumatra)\",\"lat\":3.9076,\"long\":96.6033},{\"wordEn\":\"support:   monetary support\",\"wordAn\":\"biaya\",\"langSubgroup\":\"WMP\",\"langName\":\"Dairi-Pakpak Batak\",\"wordEnLong\":\"costs, expenses (as for a feast); money to spend on a journey\",\"setnote\":\"Borrowing, ultimately from Sanskrit.\",\"origin\":\"Sanskrit\",\"originForeign\":true,\"langISOCode\":\"btd\",\"langISOName\":\"Batak Dairi\",\"langISOLink\":\"http://www.ethnologue.com/show_language.asp?code=btd\",\"langLocation\":\"Indonesia (Sumatra)\"},{\"wordEn\":\"support:   monetary support\",\"wordAn\":\"biyaya(h)\",\"langSubgroup\":\"WMP\",\"langName\":\"Javanese\",\"wordEnLong\":\"cost, outlay\",\"setnote\":\"Borrowing, ultimately from Sanskrit.\",\"origin\":\"Sanskrit\",\"originForeign\":true,\"langISOCode\":\"jav\",\"langISOLink\":\"http://www.ethnologue.com/show_language.asp?code=jav\",\"langLocation\":\"Indonesia (Java and Bali)\",\"lat\":-7.406,\"long\":110.9619},{\"wordEn\":\"support:   monetary support\",\"wordAn\":\"biyaya(h)\",\"langSubgroup\":\"WMP\",\"langName\":\"Javanese\",\"wordEnLong\":\"cost, outlay\",\"setnote\":\"Borrowing, ultimately from Sanskrit.\",\"origin\":\"Sanskrit\",\"originForeign\":true,\"langISOCode\":\"jav\",\"langISOLink\":\"http://www.ethnologue.com/show_language.asp?code=jav\",\"langLocation\":\"Indonesia (Java and Bali)\",\"lat\":-7,\"long\":111},{\"wordEn\":\"support:   monetary support\",\"wordAn\":\"biyaya(h)\",\"langSubgroup\":\"WMP\",\"langName\":\"Javanese\",\"wordEnLong\":\"cost, outlay\",\"setnote\":\"Borrowing, ultimately from Sanskrit.\",\"origin\":\"Sanskrit\",\"originForeign\":true,\"langISOCode\":\"jav\",\"langISOLink\":\"http://www.ethnologue.com/show_language.asp?code=jav\",\"langLocation\":\"Indonesia (Java and Bali)\"},{\"wordEn\":\"support:   monetary support\",\"wordAn\":\"biyaya\",\"langSubgroup\":\"WMP\",\"langName\":\"Gorontalo\",\"wordEnLong\":\"costs, expenses\",\"setnote\":\"Borrowing, ultimately from Sanskrit.\",\"origin\":\"Sanskrit\",\"originForeign\":true,\"langISOCode\":\"gor\",\"langISOLink\":\"http://www.ethnologue.com/show_language.asp?code=gor\",\"langLocation\":\"Indonesia (Sulawesi)\",\"lat\":0.5493,\"long\":122.6733}]"]
